{
  "title": "첫 TOPIK 시험",
  "all": [
    {
      "ko": "내일은 드디어 첫 번째 TOPIK 시험이에요.",
      "zh": "明天終於是第一次的TOPIK考試了。"
    },
    {
      "ko": "저는 한국어를 배운 지 일 년이 되었어요.",
      "zh": "我學韓語已經一年了。"
    },
    {
      "ko": "오늘 밤에 마지막으로 책을 다시 봐야 해요.",
      "zh": "今天晚上要最後再看一次書。"
    },
    {
      "ko": "책상 위에는 단어장과 문법책이 있어요.",
      "zh": "書桌上有單字本和文法書。"
    },
    {
      "ko": "조금 긴장되지만 열심히 준비했어요.",
      "zh": "雖然有點緊張，但是我認真準備了。"
    },
    {
      "ko": "어머니께서 따뜻한 차를 가져다 주셨어요.",
      "zh": "媽媽幫我端來了溫熱的茶。"
    },
    {
      "ko": "\"너무 걱정하지 마.\" 라고 어머니께서 말씀하셨어요.",
      "zh": "媽媽說：「不要太擔心。」"
    },
    {
      "ko": "열두 시쯤에 잠자리에 들었어요.",
      "zh": "大概十二點左右上床睡覺。"
    },
    {
      "ko": "아침 일찍 일어나서 아침을 먹었어요.",
      "zh": "早上很早起來吃了早餐。"
    },
    {
      "ko": "신분증과 수험표를 가방에 잘 넣었어요.",
      "zh": "把身分證和准考證好好放進了書包。"
    },
    {
      "ko": "지하철을 타고 시험장에 갔어요.",
      "zh": "搭地鐵去了考場。"
    },
    {
      "ko": "시험장 앞에는 사람이 정말 많았어요.",
      "zh": "考場前面真的有很多人。"
    },
    {
      "ko": "외국 학생들도 많이 보였어요.",
      "zh": "也看到了很多外國學生。"
    },
    {
      "ko": "교실에 들어가서 자리를 찾았어요.",
      "zh": "進到教室找到了座位。"
    },
    {
      "ko": "감독관 선생님께서 규칙을 설명해 주셨어요.",
      "zh": "監考老師為我們說明了規則。"
    },
    {
      "ko": "먼저 듣기 시험이 시작되었어요.",
      "zh": "首先聽力測驗開始了。"
    },
    {
      "ko": "한국 사람의 발음이 빨라서 조금 어려웠어요.",
      "zh": "韓國人的發音很快，有點困難。"
    },
    {
      "ko": "그래도 아는 단어가 많이 나왔어요.",
      "zh": "不過出現了很多我知道的單字。"
    },
    {
      "ko": "다음은 읽기 시험이었어요.",
      "zh": "接下來是閱讀測驗。"
    },
    {
      "ko": "지문이 길어서 시간이 부족할까 봐 걱정했어요.",
      "zh": "因為文章很長，所以擔心時間會不夠。"
    },
    {
      "ko": "문제를 천천히 잘 읽고 답을 골랐어요.",
      "zh": "我慢慢仔細讀題目，然後選了答案。"
    },
    {
      "ko": "모르는 문제는 일단 표시해 두었어요.",
      "zh": "不會的題目先做了記號。"
    },
    {
      "ko": "마지막에 다시 한번 확인했어요.",
      "zh": "最後再確認了一次。"
    },
    {
      "ko": "\"시험 종료.\" 라는 소리가 들렸어요.",
      "zh": "聽到了「考試結束」的聲音。"
    },
    {
      "ko": "시험지를 내고 교실에서 나왔어요.",
      "zh": "交了考卷，從教室出來了。"
    },
    {
      "ko": "밖에는 햇빛이 아주 밝았어요.",
      "zh": "外面的陽光非常明亮。"
    },
    {
      "ko": "친구가 시험장 앞에서 기다리고 있었어요.",
      "zh": "朋友在考場前面等著我。"
    },
    {
      "ko": "우리는 같이 점심을 먹으러 갔어요.",
      "zh": "我們一起去吃午餐了。"
    },
    {
      "ko": "결과는 모르지만 최선을 다해서 후회는 없어요.",
      "zh": "雖然不知道結果，但因為盡了全力所以沒有後悔。"
    },
    {
      "ko": "다음에는 더 높은 급수에 도전하고 싶어요.",
      "zh": "下次想挑戰更高的級數。"
    },
    {
      "ko": "시험장 위치를 미리 확인해 두었어요.",
      "zh": "我事先確認好了考場的位置。"
    },
    {
      "ko": "듣기 영역이 제일 자신이 없어요.",
      "zh": "聽力部分我最沒有信心。"
    },
    {
      "ko": "수험표와 신분증을 가방에 넣었어요.",
      "zh": "我把准考證和身分證放進了包包裡。"
    },
    {
      "ko": "연필과 지우개도 여러 개 준비했어요.",
      "zh": "我也準備了好幾枝鉛筆和橡皮擦。"
    },
    {
      "ko": "긴장해서 어젯밤에 잠을 설쳤어요.",
      "zh": "因為緊張，昨晚我沒睡好。"
    },
    {
      "ko": "쓰기 시험에서는 글자 수를 꼭 맞춰야 해요.",
      "zh": "寫作測驗一定要符合字數要求。"
    },
    {
      "ko": "읽기 문제는 시간이 부족할까 봐 걱정돼요.",
      "zh": "閱讀題我擔心時間會不夠。"
    },
    {
      "ko": "모의고사를 풀면서 실력을 점검했어요.",
      "zh": "我透過做模擬考來檢驗自己的實力。"
    },
    {
      "ko": "헷갈리는 문법은 표로 정리해 두었어요.",
      "zh": "容易混淆的文法我整理成了表格。"
    },
    {
      "ko": "급수를 따면 대학에 지원할 수 있어요.",
      "zh": "考到級數的話就能申請大學了。"
    },
    {
      "ko": "시험 시작 삼십 분 전까지 입실해야 해요.",
      "zh": "必須在考試開始前三十分鐘入場。"
    },
    {
      "ko": "답안지에 답을 옮겨 적을 시간도 남겨야 해요.",
      "zh": "也得留下把答案謄寫到答案卡的時間。"
    },
    {
      "ko": "휴대폰은 미리 전원을 꺼서 제출했어요.",
      "zh": "手機要事先關機並交出去。"
    },
    {
      "ko": "긴 지문은 핵심만 빠르게 읽는 연습을 했어요.",
      "zh": "長篇文章我練習了只快速抓重點來讀。"
    },
    {
      "ko": "합격 점수를 넘기는 것이 이번 목표예요.",
      "zh": "超過及格分數是我這次的目標。"
    },
    {
      "ko": "쉬는 시간에 초콜릿을 먹으면 도움이 된대요.",
      "zh": "聽說休息時間吃巧克力會有幫助。"
    },
    {
      "ko": "어려운 단어는 손바닥에 쓰며 외웠어요.",
      "zh": "難的單字我邊寫在手掌上邊背。"
    },
    {
      "ko": "시험 결과는 몇 주 뒤에 발표된대요.",
      "zh": "聽說考試結果幾週後會公布。"
    },
    {
      "ko": "선생님이 마지막으로 격려의 말을 해 주셨어요.",
      "zh": "老師最後給了我鼓勵的話。"
    },
    {
      "ko": "아침은 든든하게 먹고 가려고 해요.",
      "zh": "我打算吃得飽飽的再去。"
    },
    {
      "ko": "지난 기출 문제를 다시 한번 훑어봤어요.",
      "zh": "我又把過去的考古題大致看了一遍。"
    },
    {
      "ko": "떨리지만 그동안 노력한 만큼 잘하고 싶어요.",
      "zh": "雖然很緊張，但想配得上這段時間的努力好好發揮。"
    }
  ]
}