{
  "title": "Video Call Across the Ocean",
  "all": [
    {
      "en": "Every Sunday evening, the Lee family had a video call with relatives in Vancouver.",
      "zh": "每個星期日晚上，李家都會和溫哥華的親戚視訊通話。"
    },
    {
      "en": "Grandpa, who was eighty years old, struggled to figure out the camera angle.",
      "zh": "八十歲的爺爺努力想搞清楚鏡頭的角度。"
    },
    {
      "en": "\"I can only see your forehead, Dad!\" Aunt Linda shouted from the screen.",
      "zh": "「爸，我只看得到你的額頭！」琳達阿姨在螢幕另一頭大喊。"
    },
    {
      "en": "Grandpa laughed and tilted the tablet up until his whole face appeared.",
      "zh": "爺爺笑了，把平板往上斜，直到整張臉都出現在畫面裡。"
    },
    {
      "en": "Cousin Ryan, who was now twelve, showed off the snow falling outside his window.",
      "zh": "已經十二歲的表弟雷恩展示著窗外飄下的雪。"
    },
    {
      "en": "His Taiwanese cousins gasped because they had never seen real snow before.",
      "zh": "他在台灣的表兄弟姊妹都驚呼起來，因為他們從來沒看過真正的雪。"
    },
    {
      "en": "Aunt Linda announced that she was finally pregnant after years of trying.",
      "zh": "琳達阿姨宣布在嘗試多年後，她終於懷孕了。"
    },
    {
      "en": "Everyone in Taiwan cheered, and Grandma started crying tears of happiness.",
      "zh": "台灣這邊的所有人都歡呼起來，奶奶開心得流下眼淚。"
    },
    {
      "en": "They talked about plans to visit each other during the summer holidays.",
      "zh": "他們聊著暑假時要互相拜訪的計畫。"
    },
    {
      "en": "Grandpa promised to bring his famous beef jerky when they flew to Canada.",
      "zh": "爺爺答應飛去加拿大時要帶上他出名的牛肉乾。"
    },
    {
      "en": "The call lasted nearly two hours and felt much shorter than that.",
      "zh": "視訊持續了快兩個小時，但感覺比實際時間短得多。"
    },
    {
      "en": "When they finally said goodbye, the distance between them felt much smaller.",
      "zh": "當他們終於說再見時，彼此之間的距離感覺縮短了許多。"
    },
    {
      "en": "After hanging up, Grandma immediately started writing a long shopping list for the Canada trip.",
      "zh": "掛掉電話後，奶奶立刻開始為加拿大之旅寫一張長長的購物清單。"
    },
    {
      "en": "She wanted to bring pineapple cakes, dried mangoes, and traditional Taiwanese tea bags.",
      "zh": "她想帶鳳梨酥、芒果乾，還有傳統的台灣茶包。"
    },
    {
      "en": "Grandpa carefully sealed his homemade beef jerky in three layers of plastic bags.",
      "zh": "爺爺仔細地把自製牛肉乾用三層塑膠袋封好。"
    },
    {
      "en": "The cousins in Taiwan started a group chat to plan activities for their Canadian relatives.",
      "zh": "台灣的表兄弟姊妹開了一個群組，為加拿大親戚規劃活動。"
    },
    {
      "en": "They suggested visiting the night markets, hot springs, and a famous fishing village.",
      "zh": "他們建議去夜市、泡溫泉，還有拜訪一個著名的漁村。"
    },
    {
      "en": "Aunt Linda replied with photos of baby clothes she had recently bought on sale.",
      "zh": "琳達阿姨回覆了她最近特價買到的嬰兒衣服照片。"
    },
    {
      "en": "Ryan promised to teach his Taiwanese cousins how to build a proper snowman next winter.",
      "zh": "雷恩答應明年冬天教他在台灣的表兄弟姊妹如何堆一個像樣的雪人。"
    },
    {
      "en": "Mom booked the flight tickets that same evening because the prices looked very reasonable.",
      "zh": "媽媽當天晚上就訂了機票，因為價格看起來非常合理。"
    },
    {
      "en": "Grandpa kept practicing simple English phrases so he could chat with Ryan's school friends.",
      "zh": "爺爺一直練習簡單的英語句子，這樣他就能和雷恩的同學聊天。"
    },
    {
      "en": "Everyone agreed that family love could easily cross any ocean, no matter how wide.",
      "zh": "大家都認為，無論海洋有多寬，家人的愛都能輕易跨越。"
    }
  ]
}
