{
  "title": "料理男子、恋をする",
  "title_zh": "料理男子，墜入愛河",
  "all": [
    {
      "ja": "翌々週、薫子の家を訪れると、もう買い物に行く準備は出来ていた。",
      "zh": "下下週,造訪薰子家時,她已經做好出門購物的準備了。"
    },
    {
      "ja": "ゲームは電源が切られていて、コートも羽織っている。",
      "zh": "遊戲機已關掉,大衣也披在身上了。"
    },
    {
      "ja": "今日は何が食べたいですか？",
      "zh": "今天想吃什麼呢?"
    },
    {
      "ja": "尋ねると、笑顔全開で、何でも！　という元気な答えが返ってきた。",
      "zh": "一問之下,得到了滿臉笑容、「什麼都好!」這樣有活力的回答。"
    },
    {
      "ja": "それ、料理人が一番いやな答えだ。",
      "zh": "那是廚師最討厭的回答。"
    },
    {
      "ja": "でも逆に料理人を信頼してくれているのだということもわかる。",
      "zh": "但反過來說,也表示對廚師非常信任。"
    },
    {
      "ja": "前回和風でしたから、今回は洋風にしましょうか？",
      "zh": "上次是日式風味,這次來個西式吧?"
    },
    {
      "ja": "ジャーマンポテトなんてどうですか？　ビールに合います",
      "zh": "德國香腸馬鈴薯如何?和啤酒很搭。"
    },
    {
      "ja": "ビールに合うご飯！　いいね、理想的だね！",
      "zh": "配啤酒的料理!好啊,真是理想!"
    },
    {
      "ja": "じゃあ。そうしましょう。",
      "zh": "那就這麼決定吧。"
    },
    {
      "ja": "野菜は、ピーマン類をさっと炒めたものにしましょうか。彩りを考えないと",
      "zh": "蔬菜就用青椒類快炒一下吧。要考慮配色才行。"
    },
    {
      "ja": "二日食べられたほうが良いですよね。量は調節しますので",
      "zh": "可以吃兩天比較好對吧?份量我會調整。"
    },
    {
      "ja": "なんてできるコックさんなのかしら！",
      "zh": "真是個能幹的廚師啊!"
    },
    {
      "ja": "お姉さん、花丸百点あげちゃう！",
      "zh": "姊姊我給你打滿分一百分!"
    },
    {
      "ja": "ねえ、佳亮くん。",
      "zh": "我說啊,佳亮。"
    },
    {
      "ja": "佳亮くんが私のご飯を作った後、家でもう一度ご飯を作らなきゃいけないんだったら、私の家で一緒に食べたらどうかな？",
      "zh": "如果佳亮做完我的飯後,還得回家再做一次的話,要不要在我家一起吃呢?"
    },
    {
      "ja": "二度ご飯を作るのも大変でしょう。私の家で食べていけば一回で済むわ",
      "zh": "做兩次飯也很辛苦吧。在我家吃完再回去的話,一次就解決了。"
    },
    {
      "ja": "薫子さんは僕と一緒でご飯食べられますか？",
      "zh": "薰子小姐能和我一起吃飯嗎?"
    },
    {
      "ja": "作った僕を目の前にして、余計な気を遣わなきゃいけないんだったら、僕は遠慮します",
      "zh": "如果做飯的我就在面前,還得多餘地顧慮我的話,我就敬謝不敏了。"
    },
    {
      "ja": "私、お世辞言うように出来てないから。",
      "zh": "我這個人不會說客套話。"
    },
    {
      "ja": "美味しかったら美味しいって言うし、不味かったら不味いっていうわ",
      "zh": "好吃就會說好吃,難吃就會說難吃。"
    },
    {
      "ja": "じゃあ、お言葉に甘えて。",
      "zh": "那麼,就恭敬不如從命了。"
    },
    {
      "ja": "そしたら材料の分量を考えないとあきませんね",
      "zh": "那食材的份量就得重新考慮一下了。"
    },
    {
      "ja": "本当に自由で手伝う気のない人だな。",
      "zh": "真是個自由自在又毫無幫忙意願的人啊。"
    },
    {
      "ja": "もう出来たの!?　私、まだクリア出来てないんだけど!?",
      "zh": "已經做好了?!我遊戲還沒破關呢!?"
    },
    {
      "ja": "今日は簡単な料理でしたからね",
      "zh": "今天是簡單的料理嘛。"
    },
    {
      "ja": "それでは！　頂きます！",
      "zh": "那麼!我要開動了!"
    },
    {
      "ja": "お…っいしー………。食欲をそそる香り、いくらでも食べられる……。ビールに合うわあ……",
      "zh": "好…好吃……。香味很促進食慾,可以吃個不停……。和啤酒真搭啊……"
    },
    {
      "ja": "はー…、ビールが染みる…。ご飯美味しい…。こんな幸せなことって、あるのねえ……",
      "zh": "啊……啤酒沁人心脾……。飯好好吃……。竟然有這麼幸福的事啊……"
    },
    {
      "ja": "これ、凄くいい香りがするわ。パプリカもシャキシャキしていて美味しいし…",
      "zh": "這個香味好棒喔。彩椒也脆脆的很好吃……"
    },
    {
      "ja": "ピーマンやパプリカが塩昆布と馴染むようにごま油で炒めてます",
      "zh": "為了讓青椒和彩椒能跟鹽昆布融合,所以用麻油炒。"
    },
    {
      "ja": "コクがあるというか、香ってくるというか…。",
      "zh": "該說很有層次,還是說很香呢……"
    },
    {
      "ja": "そして、舌に馴染むようにほっとするこの味は塩昆布なのね…。",
      "zh": "然後,這種讓人安心、貼合舌頭的味道是鹽昆布啊……"
    },
    {
      "ja": "佳亮くん、またまたにくいことするわね……",
      "zh": "佳亮,你又做了讓人佩服的事啊……"
    },
    {
      "ja": "お肉を焼いただけのステーキだって美味しいでしょう。",
      "zh": "只是把肉烤一烤的牛排也很好吃對吧。"
    },
    {
      "ja": "あれは、お肉のたんぱく質を構成するアミノ酸のグルタミン酸の旨味です。",
      "zh": "那是構成肉類蛋白質的胺基酸——麩胺酸的鮮味。"
    },
    {
      "ja": "割とどんな食材でも旨味は含まれていて、だから食材そのままを食べても美味しいと思えるのはその所為です",
      "zh": "幾乎所有食材都含有鮮味,所以就算只吃食材本身也覺得好吃,就是這個緣故。"
    },
    {
      "ja": "そうか、野菜を生で食べてもほんのり甘いものね。あれも旨味なのか…",
      "zh": "原來如此,生吃蔬菜也會有淡淡的甜味呢。那也是鮮味啊……"
    },
    {
      "ja": "これがあれば一晩中ビールが飲んでいられる……。美味しい……",
      "zh": "有這個的話,一整晚都能喝啤酒……。好好吃……"
    },
    {
      "ja": "明日も美味しいビールが飲めるわ…。これを幸せと言わずに何を幸せというのか……",
      "zh": "明天也能喝到美味的啤酒了……。如果這不叫幸福,那什麼才叫幸福呢……"
    },
    {
      "ja": "喜んでいただけて何よりだ",
      "zh": "能讓您高興真是太好了。"
    },
    {
      "ja": "ようよう杉山。一人で自作の昼飯食ってねーで、たまには外飯付き合えよ",
      "zh": "喂喂杉山,別一個人吃自製便當,偶爾也來外面吃個飯吧。"
    },
    {
      "ja": "えっ、杉山、それ自前の弁当？　すげー完成度じゃん。",
      "zh": "咦,杉山,那是你自己做的便當?完成度好高啊。"
    },
    {
      "ja": "俺、彼女の手作りかと思ってたわ",
      "zh": "我還以為是你女友親手做的呢。"
    },
    {
      "ja": "俺もこいつの手作りだって知ったときはびっくりした。こんな細かいこと、良く出来るよなあ",
      "zh": "我知道是這傢伙親手做的時候也嚇了一跳。這麼細的活兒,虧他做得來啊。"
    },
    {
      "ja": "いやいや、そもそもコロッケ自分で作るとか！　もう俺なんて総菜コーナーだよ",
      "zh": "不不,自己做可樂餅之類的耶!像我都直接買熟食區的。"
    },
    {
      "ja": "俺だってそうだよ。揚げもんのあったかいのなんて、店で食べたほうが美味しいもんなあ",
      "zh": "我也是啊。熱呼呼的炸物在店裡吃比較好吃嘛。"
    },
    {
      "ja": "だから女に振られちまうんだろうなあ。",
      "zh": "所以才會被女生甩吧。"
    },
    {
      "ja": "俺が女だったら、そんな料理上手と比べられたらたまんねーもんなあ",
      "zh": "我要是女生,被人拿來和那種廚藝高手比較才受不了呢。"
    },
    {
      "ja": "いっそ、家事料理壊滅的な女と付き合えば、ありがたがってくれるんじゃね？　むしろ離してくれないと思うぜ",
      "zh": "乾脆找個家事料理完全不行的女生交往,她說不定會感激你呢?反而會緊抓著不放喔。"
    },
    {
      "ja": "そういうわけで、俺は女性受けが悪いんやから、合コンなんかに誘わんといてな。",
      "zh": "所以說,我女人緣本來就差,聯誼之類的別找我啦。"
    },
    {
      "ja": "どうせ、珍獣を見るような目で見られんねんから、こっちもイラつくだけやし",
      "zh": "反正會被當成珍獸看待,我這邊也只會火大而已。"
    },
    {
      "ja": "全く、会話のせいで弁当が不味くなってしまった。",
      "zh": "真是的,因為對話讓便當變得不好吃了。"
    },
    {
      "ja": "か…っ、薫子さーーーんっ！",
      "zh": "薰…薰子小姐——!"
    },
    {
      "ja": "佳亮くんじゃない、どうしたの、こんな遅くに",
      "zh": "這不是佳亮嗎,怎麼這麼晚還跑來?"
    },
    {
      "ja": "あら、振り込めてたのね。良かったわ",
      "zh": "哎呀,順利匯出去了啊。太好了。"
    },
    {
      "ja": "ふ…っ、振り込めてたのね、じゃないです！　なんですか、この金額は！",
      "zh": "什、什麼順利匯出去了!這金額是怎麼回事!"
    },
    {
      "ja": "あら、足りなかった？",
      "zh": "哎呀,不夠嗎?"
    },
    {
      "ja": "一体、何のつもりでこんな大金振り込んだんですか！",
      "zh": "到底是打什麼主意匯這麼大筆錢的!"
    },
    {
      "ja": "ご飯のお代を支払うから、口座教えてって",
      "zh": "我說要付飯錢,所以告訴我帳號吧。"
    },
    {
      "ja": "月にたった二回。それもごくありふれた普通のご飯を食べただけで、貴女はこんな大金を店に支払うんですか!?",
      "zh": "一個月才兩次。而且只是吃了極普通的家常飯,妳會付店裡這麼大筆錢嗎!?"
    },
    {
      "ja": "銀座の三ツ星レストランでも、こんなに取らないぞ",
      "zh": "就算是銀座的三星餐廳也不會收這麼多啊。"
    },
    {
      "ja": "ごめんなさい。相場が分からなかったの…",
      "zh": "對不起。我不知道行情……"
    },
    {
      "ja": "兎に角、これはいったんお返しします。こんなの受け取れない",
      "zh": "總之,這個我先還給妳。我不能收這種東西。"
    },
    {
      "ja": "そんな…。困るわ、私、こういう風にしか、お礼が出来ないのよ……",
      "zh": "怎麼這樣……。傷腦筋耶,我只能用這種方式表達謝意啊……"
    },
    {
      "ja": "薫子さんに出来ること、あるじゃないですか",
      "zh": "薰子小姐妳能做的事情,不是有嗎?"
    },
    {
      "ja": "僕の料理、食べてくれるじゃないですか",
      "zh": "妳願意吃我做的料理啊。"
    },
    {
      "ja": "良いんですよ、お礼なんて",
      "zh": "不用啦,什麼謝禮的。"
    },
    {
      "ja": "困るわ……。そんなこと言われたら、私、本当に、どうしたらいいのか分からない……",
      "zh": "傷腦筋耶……。你這樣說,我真的不知道該怎麼辦才好……"
    },
    {
      "ja": "料理が美味しかった時は、僕にコーヒーをご馳走してください。コンビニの缶コーヒーで構いません。",
      "zh": "料理好吃的時候,請我喝杯咖啡就好。便利商店的罐裝咖啡也沒關係。"
    },
    {
      "ja": "僕はお酒をあまり飲まへんし、コーヒーは好きです。",
      "zh": "我不太喝酒,但喜歡咖啡。"
    },
    {
      "ja": "それに、薫子さんやってコンビニへ行くのは好きでしょう？",
      "zh": "而且薰子小姐妳也喜歡去便利商店吧?"
    },
    {
      "ja": "そんなことで、良いのかしら……",
      "zh": "這樣就可以了嗎……?"
    },
    {
      "ja": "良いんですよ。僕が、薫子さんに料理を作ってあげたいだけなので、本当ならお礼なんて要らないんです",
      "zh": "可以啦。我只是想為薰子小姐做菜,其實連謝禮都不需要的。"
    },
    {
      "ja": "お弁当、持って行ったらどうかな。会社だから嫌がるかな。",
      "zh": "帶便當去如何呢。在公司會不會被嫌棄呢。"
    },
    {
      "ja": "大瀧さんに用事があってきたんですが、会えますか？",
      "zh": "我有事找大瀧小姐,能見到她嗎?"
    },
    {
      "ja": "大瀧ですか？　ご案内します。此方へどうぞ",
      "zh": "您找大瀧嗎?我來帶路。請走這邊。"
    },
    {
      "ja": "うわ、ホンマに忙しそう…。呑気にお弁当持ってきてもうたけど、失敗やったかもしれへん……",
      "zh": "哇,真的好忙的樣子……。我悠哉地帶便當來,可能失敗了……"
    },
    {
      "ja": "社長、お客様です",
      "zh": "社長,有客人來訪。"
    },
    {
      "ja": "佳亮くん、無理言って悪かったわね。まあ、座って",
      "zh": "佳亮,讓你勉強跑這一趟真是抱歉。來,坐吧。"
    },
    {
      "ja": "しゃ、社長だったのか……",
      "zh": "原、原來是社長啊……"
    },
    {
      "ja": "今、リニューアルオープンの店舗の納期直前で忙しくて…。",
      "zh": "現在因為翻新開幕的店面快到交期了,忙得不可開交……"
    },
    {
      "ja": "全然家にも帰れないし食事も不規則になるから、ほら、吹き出物も出ちゃって",
      "zh": "完全沒辦法回家,吃飯也不規律,你看,連痘痘都長出來了。"
    },
    {
      "ja": "お弁当、楽しみにしてたのよ",
      "zh": "便當,我一直很期待呢。"
    },
    {
      "ja": "ちょっと残り物で申し訳ないんですけど…",
      "zh": "用了一些剩菜,真不好意思……"
    },
    {
      "ja": "うん、美味しい。元気が出るわ。ありがとう、佳亮くん",
      "zh": "嗯,好吃。讓我有精神了。謝謝你,佳亮。"
    },
    {
      "ja": "薫子さん。週末だけでも部屋に帰って来れませんか？",
      "zh": "薰子小姐,至少週末能不能回房間呢?"
    },
    {
      "ja": "今までみたいに食事を一緒に摂ることは難しいと思いまけど、お弁当くらいやったら差し入れできます",
      "zh": "雖然像之前那樣一起吃飯有困難,但便當這種程度的話我可以送過去。"
    },
    {
      "ja": "もう何日もカップラーメンで、流石に飽きてたのよ…。",
      "zh": "好幾天都吃泡麵,實在膩了……"
    },
    {
      "ja": "部屋には帰れないけど、受付に託（ことづ）けてくれたら受け取れるように手配しておくから、佳亮くんの都合のいい時に食べさせてもらいたい。",
      "zh": "我沒辦法回房間,但如果你交給接待處,我會安排好讓我能拿到,所以希望你方便的時候做給我吃。"
    },
    {
      "ja": "この忙しいのは春になれば終わるから",
      "zh": "這個忙的時期一到春天就結束了。"
    },
    {
      "ja": "ほな、僕は帰りますんで",
      "zh": "那麼,我就先回去了。"
    },
    {
      "ja": "ちょっと休憩ついでにコーヒーを買いに行くわ。お弁当のお礼",
      "zh": "我順便休息一下去買咖啡。當作便當的謝禮。"
    },
    {
      "ja": "あ、ぶない！",
      "zh": "啊,危險!"
    },
    {
      "ja": "歩道は歩行者優先なのに、なんて自転車なの",
      "zh": "人行道明明是行人優先,那是什麼樣的腳踏車啊。"
    },
    {
      "ja": "あー、びっくりした…。薫子さん、ありがとう",
      "zh": "啊—嚇我一跳……。薰子小姐,謝謝妳。"
    },
    {
      "ja": "杉山くん",
      "zh": "杉山。"
    },
    {
      "ja": "ふふ、変わらずだなあ。中田原くんたちがお花見計画してるけど、貴方は行かないの？",
      "zh": "呵呵,還是老樣子啊。中田原他們在計畫賞花,你不去嗎?"
    },
    {
      "ja": "あー、僕は不参加ですねえ。僕、女性受けが悪いので、女性が同席の飲み会には出ないです",
      "zh": "啊,我不參加。我女人緣不好,所以有女性在的酒會我不去。"
    },
    {
      "ja": "杉山くん、かわいい顔してるんだから、女の子受けは良いでしょう？",
      "zh": "杉山你長得這麼可愛,應該很受女生歡迎才對吧?"
    },
    {
      "ja": "僕、料理男子なんで、料理する男って女の人は比べられるみたいで嫌がられます。",
      "zh": "我是料理男子,會做飯的男生好像會讓女生覺得被比較而討厭。"
    },
    {
      "ja": "経験上知ってるので、行かないです",
      "zh": "經驗告訴我這點,所以不去。"
    },
    {
      "ja": "ちなみに、お料理の腕前は如何ほど？",
      "zh": "順便問一下,你的廚藝程度如何?"
    },
    {
      "ja": "毎日の昼の弁当、自作です",
      "zh": "每天的午餐便當都是自己做的。"
    },
    {
      "ja": "すっごいじゃない！",
      "zh": "好厲害啊!"
    },
    {
      "ja": "何時も杉山くんのお弁当って彩りも良いし、食べ応えがありそうで、きっとお母様が息子さん思いなんだわって思っていたわ",
      "zh": "我一直覺得杉山的便當配色又好、份量看起來又夠,還想說一定是令堂疼愛兒子。"
    },
    {
      "ja": "よし、杉山くん。中田原くんたちに負けずに、お花見行こうよ、一緒に",
      "zh": "好,杉山。不要輸給中田原他們,一起去賞花吧。"
    },
    {
      "ja": "駄目かな。出来れば是非、一緒に行って欲しい",
      "zh": "不行嗎?可以的話,真希望你一起去。"
    },
    {
      "ja": "うわあ、なんか見ちゃいけないものを見ちゃった気分！",
      "zh": "哇,感覺看到了不該看的東西!"
    },
    {
      "ja": "今度、どういう顔で佳亮くんに会えば良い!?",
      "zh": "下次該用什麼表情面對佳亮才好啊!?"
    },
    {
      "ja": "見ちゃいけない。あれは私が知らない佳亮くんの顔。",
      "zh": "不可以看。那是我所不知道的佳亮的一面。"
    },
    {
      "ja": "佳亮くんにだってプライベートがある。",
      "zh": "佳亮也有他的私生活。"
    },
    {
      "ja": "今日は、ごぼうとニンジンのハンバーグと、豆腐としめじと豚肉の卵とじです",
      "zh": "今天是牛蒡紅蘿蔔漢堡排,還有豆腐、鴻禧菇與豬肉的滑蛋。"
    },
    {
      "ja": "今日も頂きま～す！",
      "zh": "今天也開動了!"
    },
    {
      "ja": "薫子さん、その手の絆創膏、どないしはりました？",
      "zh": "薰子小姐,妳手上的OK繃是怎麼了?"
    },
    {
      "ja": "会社で要らない書類を分別してた時に切っちゃったのよ。紙ってよく切れるよね～",
      "zh": "在公司分類不要的文件時被割到的。紙還真容易割傷人呢——"
    },
    {
      "ja": "ああ、紙はスパッと行きますからね。気を付けてください。折角きれいな指やのに",
      "zh": "啊,紙切下去很俐落的。請小心點。難得有這麼漂亮的手指。"
    },
    {
      "ja": "私にきれいなんて言葉、似合わないよ、佳亮くん",
      "zh": "「漂亮」這種詞不適合我啦,佳亮。"
    },
    {
      "ja": "薫子さん、顔、めっちゃきれいですよ？",
      "zh": "薰子小姐,妳的臉超漂亮的喔?"
    },
    {
      "ja": "僕最初にコンビニ一緒に行った時にめちゃくちゃきれいな顔の人やって思うたって言うたでしょ？",
      "zh": "我第一次跟妳一起去便利商店時就說過妳是個臉蛋超漂亮的人吧?"
    },
    {
      "ja": "自覚ありません？",
      "zh": "妳沒自覺嗎?"
    },
    {
      "ja": "いや、私、周りから女扱いされないし。そういう形容詞もあんまり聞かないし",
      "zh": "不,我周圍的人都不把我當女人看,也很少聽到那種形容詞。"
    },
    {
      "ja": "女扱いされないのは周りがどうかと思いますけど、…僕もどうかと思いますけど、薫子さんは本当にきれいな顔をしてますからね？",
      "zh": "不被當女人看待是周圍的人有問題……我也是覺得這樣不對,薰子小姐妳真的長得很漂亮喔?"
    },
    {
      "ja": "遠目にイケメンに見えますけど",
      "zh": "遠遠看的話像個帥哥就是了。"
    },
    {
      "ja": "うん。良く男と間違われる",
      "zh": "嗯,常被誤認為男生。"
    },
    {
      "ja": "でも、きれいな指なんですから、大事にしてくださいね",
      "zh": "不過,這麼漂亮的手指,請好好愛惜喔。"
    },
    {
      "ja": "あれ？",
      "zh": "咦?"
    },
    {
      "ja": "わ、わーわー！　見ちゃ駄目！　見ないで！",
      "zh": "哇、哇—哇—!不可以看!不要看!"
    },
    {
      "ja": "か、かおるこさん……？",
      "zh": "薰、薰子小姐……?"
    },
    {
      "ja": "どないしたはったんですか、薫子さん。ゴミが捨てられません",
      "zh": "妳怎麼了啊,薰子小姐。垃圾沒辦法丟啊。"
    },
    {
      "ja": "いやあ、柄にないことをしたわ。やっぱり料理は佳亮くんに作ってもらった方が良いね！",
      "zh": "唉,做了不適合我的事呢。果然料理還是請佳亮做比較好啊!"
    },
    {
      "ja": "薫子さん、どうしちゃったんですか、一体…",
      "zh": "薰子小姐,妳到底是怎麼了……?"
    },
    {
      "ja": "……女なら、やっぱり料理のひとつでも出来ないと駄目なのかな、って、ちょっと思ったのよ。",
      "zh": "……我有點在想,身為女人,還是得會做一道料理才行吧。"
    },
    {
      "ja": "でも、私には向かないわ。やっぱり佳亮くんに作ってもらう",
      "zh": "但是,我不適合啊。果然還是請佳亮做。"
    },
    {
      "ja": "そういう約束じゃないですか",
      "zh": "本來就是這樣約定的吧。"
    },
    {
      "ja": "うん、そうだったね。これからもよろしく！",
      "zh": "嗯,沒錯呢。今後也請多多指教!"
    },
    {
      "ja": "今日はジャガイモのガレットとミートソースです。",
      "zh": "今天是馬鈴薯煎餅和肉醬。"
    },
    {
      "ja": "ミートソースはタッパーに入れて冷凍してくださいね。",
      "zh": "肉醬請裝進保鮮盒冷凍喔。"
    },
    {
      "ja": "パスタやご飯にかけると簡単にミートソースパスタやドリアが出来ます",
      "zh": "淋在義大利麵或飯上,就能簡單做成肉醬義大利麵或焗飯。"
    },
    {
      "ja": "何時もながらありがとう～。パスタは茹でられないけど、ご飯ならレンチン出来るわ",
      "zh": "一如往常謝謝你——義大利麵我不會煮,但飯可以微波。"
    },
    {
      "ja": "んん～、ほっぺたが落ちるとはこのことね！",
      "zh": "嗯——好吃到掉下巴就是這種感覺啊!"
    },
    {
      "ja": "私、生ハムと目玉焼きを乗せないでも、ガレットだけでビールいけちゃう",
      "zh": "我不放生火腿和荷包蛋,光是煎餅本身就能配啤酒了。"
    },
    {
      "ja": "ジャガイモも千切りで炒めてあるから、ちょうどポテトスナックのようにカリカリでしょう",
      "zh": "馬鈴薯也切絲炒過,就像洋芋零食一樣脆脆的吧。"
    },
    {
      "ja": "えっ、もう帰るの？",
      "zh": "咦,要回去了嗎?"
    },
    {
      "ja": "コーヒー、まだだよ？",
      "zh": "咖啡還沒呢?"
    },
    {
      "ja": "薫子さん、お疲れでしょ。今日は帰りますね。",
      "zh": "薰子小姐妳累了吧。今天我就先回去了。"
    },
    {
      "ja": "また元気な時に、コーヒーご馳走してください",
      "zh": "等妳有精神的時候,再請我喝咖啡吧。"
    },
    {
      "ja": "疲れてなんか、ないけど……",
      "zh": "我才沒有累……"
    },
    {
      "ja": "おやすみなさい。戸締り、忘れないで",
      "zh": "晚安。別忘了鎖門喔。"
    },
    {
      "ja": "申し訳ありません。大瀧はここ暫くお休みを頂いております",
      "zh": "非常抱歉。大瀧最近請假休息中。"
    },
    {
      "ja": "病気でしょうか？　マンションには居ない気がするのですが…",
      "zh": "是生病了嗎?她好像沒在公寓裡……"
    },
    {
      "ja": "詳しいことは此処では分かりかねます",
      "zh": "詳細情況我在這裡無法回答您。"
    },
    {
      "ja": "何方か、事情の分かる方はいらっしゃいませんか？　安否が分かればいいんです",
      "zh": "有沒有任何了解情況的人呢?我只要知道她平安就好。"
    },
    {
      "ja": "大瀧がお世話になっております。私、大瀧付き秘書の佐々木と申します",
      "zh": "承蒙您照顧大瀧。我是大瀧的隨身秘書,佐佐木。"
    },
    {
      "ja": "杉山と申します。",
      "zh": "我叫杉山。"
    },
    {
      "ja": "あの、大瀧さんがお休みされているとお伺いしたんですが、大瀧さんはマンションに居ないと思うんです。",
      "zh": "那個,我聽說大瀧小姐請假了,但我想她也不在公寓裡。"
    },
    {
      "ja": "ご旅行かなにかでしょうか？",
      "zh": "是去旅行還是怎麼了嗎?"
    },
    {
      "ja": "マンションというのは、大瀧が所有しているマンション、ということですか？",
      "zh": "您說的公寓,是指大瀧持有的公寓嗎?"
    },
    {
      "ja": "所有…っていうか、住んではるマンションです。僕のマンションの向かいのマンションで…",
      "zh": "持有……應該說是她住的公寓。在我公寓對面的那棟……"
    },
    {
      "ja": "御園駅から歩いて十分ほどにあるマンションです。ご存じないですか？",
      "zh": "從御園站走路約十分鐘的公寓。您不知道嗎?"
    },
    {
      "ja": "すみません…。会社には自宅に居ると連絡が入っているのですが…",
      "zh": "對不起……。公司接到的通知是她待在自宅……"
    },
    {
      "ja": "もしよろしければ",
      "zh": "若是方便的話"
    },
    {
      "ja": "大瀧の自宅に行かれますか？",
      "zh": "您要去大瀧的自宅看看嗎?"
    },
    {
      "ja": "杉山さま、でございますね？",
      "zh": "您是杉山先生對嗎?"
    },
    {
      "ja": "杉山さまのことは、薫子さまから少しお伺いしております。",
      "zh": "杉山先生的事,我從薰子小姐那兒略有耳聞。"
    },
    {
      "ja": "私は大瀧家の執事をしております、白樺と申します。今日は良くお越しくださいました",
      "zh": "我是大瀧家的管家,我叫白樺。今天歡迎您大駕光臨。"
    },
    {
      "ja": "薫子さまのことは、ご幼少の頃からお傍で拝見しておりました。",
      "zh": "薰子小姐的事,我從她小時候就在身旁看著她長大。"
    },
    {
      "ja": "本日、杉山さまにお越しいただいて、感謝しております",
      "zh": "今日杉山先生願意前來,我們深表感謝。"
    },
    {
      "ja": "さ、ご挨拶はこのくらいにして、薫子さまのお部屋にご案内いたします。",
      "zh": "好,問候就到此為止,我帶您去薰子小姐的房間。"
    },
    {
      "ja": "社長。佐々木です",
      "zh": "社長,我是佐佐木。"
    },
    {
      "ja": "なに？",
      "zh": "什麼事?"
    },
    {
      "ja": "よ、佳亮くん……",
      "zh": "佳、佳亮……"
    },
    {
      "ja": "薫子さん、病気やったんですね…。",
      "zh": "薰子小姐,妳生病了啊……"
    },
    {
      "ja": "僕、暫くマンションの明かりが灯らへんかったから、またお仕事忙しくて帰れへんのかと勝手に思うてお弁当差し入れに行ってしもたんですけど、余計なお世話でしたね。",
      "zh": "我看公寓有段時間沒亮燈,還擅自以為妳又因為工作忙得回不來,所以送便當過去,結果是多管閒事了。"
    },
    {
      "ja": "ゆっくり休んで、早く良ぉなってください",
      "zh": "請好好休息,早日康復。"
    },
    {
      "ja": "まって！　待って、佳亮くん。…その、手に持ってるの、お弁当？",
      "zh": "等等!等等,佳亮。……那個,你手上拿的是便當嗎?"
    },
    {
      "ja": "た、食べる……。佳亮くんのお弁当、食べたい……",
      "zh": "我、我要吃……。我想吃佳亮做的便當……"
    },
    {
      "ja": "大丈夫ですか？　気を遣こてもろてんのやったら、良いですよ？",
      "zh": "妳沒事吧?如果是顧慮我的話就不用了喔?"
    },
    {
      "ja": "薫子さん、病気なんやから、おかゆさんでも食べたほうが…",
      "zh": "薰子小姐,妳在生病,還是吃點粥比較好……"
    },
    {
      "ja": "病気じゃないの…。だから、お弁当食べたい……",
      "zh": "我不是生病啦……。所以,我想吃便當……"
    },
    {
      "ja": "肉じゃが、ほうれんそうのお浸し、鰆の魚の味噌焼き、卵焼き、ブロッコリーのチーズ焼き、ケチャップスパゲティ…。すごいね、何時もながら",
      "zh": "馬鈴薯燉肉、菠菜涼拌、味噌烤鰆魚、煎蛋、起司焗花椰菜、番茄醬義大利麵……。一如往常,真厲害。"
    },
    {
      "ja": "美味しい…。美味しいよ、佳亮くん……",
      "zh": "好吃……。好吃啊,佳亮……"
    },
    {
      "ja": "どうしたんですか、薫子さん。こんなの、何時も食べてるやないですか",
      "zh": "薰子小姐怎麼了?這些妳不是平常都在吃嗎?"
    },
    {
      "ja": "うん…、でも、何時も美味しいなあって思って。…嬉しくなっちゃった…",
      "zh": "嗯……可是,我每次都覺得好好吃。……所以變得很開心……"
    },
    {
      "ja": "病気が治ったら、また料理作りますよ。だから早く良ぉなってください",
      "zh": "病好了之後,我會再做料理的。所以請早日康復。"
    },
    {
      "ja": "薫子さまがお食事を召し上がって下ってようございました。",
      "zh": "薰子小姐肯吃飯了真是太好了。"
    },
    {
      "ja": "薫子さまはお帰りになってから全くお食事を召し上がって下さらなかったのです",
      "zh": "薰子小姐回來之後完全不肯進食。"
    },
    {
      "ja": "薫子さん、そんなに具合悪かったんですか…？",
      "zh": "薰子小姐有那麼不舒服嗎……?"
    },
    {
      "ja": "お医者様もお呼びしたのですが、精神的なものだろうと言われまして…。",
      "zh": "我們也請了醫生來,但被告知說是精神方面的問題……"
    },
    {
      "ja": "ですので、私どももあれこれ手を尽くしたのですが、どうしても食べてくださらなくて…",
      "zh": "因此我們也想盡了辦法,但她無論如何就是不肯吃……"
    },
    {
      "ja": "次は薫子さまとご一緒にいらしてくださいませ",
      "zh": "下次請和薰子小姐一同前來。"
    },
    {
      "ja": "この前はごめんね。みっともないところを見せて",
      "zh": "上次對不起。讓你看到我那麼難堪的樣子。"
    },
    {
      "ja": "薫子さんが病気やったなんて知りませんでした。僕こそずかずか押しかけてもーてすみませんでした",
      "zh": "我不知道薰子小姐妳生病了。我才該道歉,擅自闖到妳家去。"
    },
    {
      "ja": "ええとね、私、オムライスが食べたいわ",
      "zh": "嗯……我想吃蛋包飯。"
    },
    {
      "ja": "オムライスって、小さい頃に食べた記憶しかないのよ",
      "zh": "蛋包飯,我只有小時候吃過的記憶。"
    },
    {
      "ja": "私、お嬢様じゃないわ。全然お嬢様っぽくないのよ。",
      "zh": "我才不是大小姐呢。完全沒有大小姐的樣子。"
    },
    {
      "ja": "昔からわんぱくだったし、小学校の頃は男子と喧嘩して生傷が絶えなかったわ。",
      "zh": "從以前就很頑皮,小學的時候和男生打架,身上的傷沒斷過。"
    },
    {
      "ja": "中学に入ったらぐんぐん背が伸びて周りの男子を威圧していたし、後輩の女子に囲まれたりしてたし",
      "zh": "上了國中身高一下子竄高,把周圍男生都壓制住了,還被學妹們圍著呢。"
    },
    {
      "ja": "社長になったのも、全然偉くないのよ。",
      "zh": "當上社長也沒什麼了不起的。"
    },
    {
      "ja": "嫁入り修行をしろって言われたから、それが嫌で仕事がしたいって言ったらあの会社を提示されて、それを受けただけ。",
      "zh": "因為被叫去做嫁妝修行,我討厭那個就說想工作,結果被安排了那家公司,只是接受了而已。"
    },
    {
      "ja": "小さい頃から弟さんや妹さんの為にお料理作ってた佳亮くんの方がうんと偉いのよ",
      "zh": "從小就為弟弟妹妹做菜的佳亮才是真的了不起。"
    },
    {
      "ja": "僕やって与えられた役目をこなしてただけですよ。",
      "zh": "我也只是把分配給我的任務做完而已。"
    },
    {
      "ja": "もし両親が弟妹の面倒を見てたら、きっと遊び呆けてたと思いますし",
      "zh": "如果爸媽有照顧弟妹的話,我大概早就玩瘋了。"
    },
    {
      "ja": "ねえ、佳亮くん。今日、私、卵を割ってみちゃ駄目かしら？",
      "zh": "我說啊,佳亮。今天,我可以試著打蛋嗎?"
    },
    {
      "ja": "どうしたんですか、急に。前、やってみたらって言うた時にやらなかったやないですか",
      "zh": "怎麼突然這樣?以前我叫妳試試看的時候妳不是不肯嗎?"
    },
    {
      "ja": "うん。…ちょっと、やってみたくなったのよ。…駄目？",
      "zh": "嗯。……就是,有點想試試看了嘛。……不行嗎?"
    },
    {
      "ja": "やっぱり私駄目ね…",
      "zh": "我果然不行啊……"
    },
    {
      "ja": "何事も最初は上手くいきませんよ",
      "zh": "凡事一開始都不會順利的。"
    },
    {
      "ja": "練習すれば割れるようになりますよ",
      "zh": "練習的話就會打蛋了。"
    },
    {
      "ja": "なりますとも",
      "zh": "當然會啊。"
    },
    {
      "ja": "これから毎回一つ、卵を割る練習をするわ。出来るようになったら褒めてね",
      "zh": "從現在起每次練習打一顆蛋。等我學會了,要誇我喔。"
    },
    {
      "ja": "頑張りましょうね",
      "zh": "一起加油吧。"
    },
    {
      "ja": "やりましたね！　薫子さん！",
      "zh": "成功了!薰子小姐!"
    },
    {
      "ja": "……できたわ……。わたし、できたわ、よしあきくん……",
      "zh": "……我做到了……。我做到了,佳亮……"
    },
    {
      "ja": "そうですよ！　立派な卵です！　おめでとうございます！",
      "zh": "沒錯!好漂亮的蛋!恭喜妳!"
    },
    {
      "ja": "…嬉しい…。少しは人並みになれたのかしら……",
      "zh": "好開心……。我有沒有稍微跟一般人接近一點了呢……"
    },
    {
      "ja": "薫子さんは、もっともっといろんなことが出来るようになりますよ。",
      "zh": "薰子小姐妳會學會越來越多事情的。"
    },
    {
      "ja": "練習すれば、オムライスだって作れます",
      "zh": "練習的話,蛋包飯也做得出來。"
    },
    {
      "ja": "そうね…。…私、頑張ってみるわ。",
      "zh": "也對……。……我會努力試試的。"
    },
    {
      "ja": "もし、オムライスを作ることが出来たら、佳亮くん、食べてくれる？",
      "zh": "如果我能做出蛋包飯,佳亮你會吃嗎?"
    },
    {
      "ja": "是非、御馳走してください。楽しみにしています",
      "zh": "請務必讓我吃。我很期待。"
    },
    {
      "ja": "佳亮くんがお料理してくれる時間を邪魔するのは悪いから",
      "zh": "我不想打擾佳亮做菜的時間。"
    },
    {
      "ja": "何を師匠ぶってんねん…。俺に習うより、あのお屋敷のシェフに習ったほうが完璧や…",
      "zh": "我裝什麼師父啊……。比起跟我學,跟那座宅邸的廚師學還更完美吧……"
    },
    {
      "ja": "卵って、平らな場所に卵の中央を軽く打ち付けてヒビを入れると、卵液に殻が混じらないのね。",
      "zh": "原來打蛋的時候,在平的地方輕輕敲蛋的中央製造裂縫,蛋液裡就不會混到蛋殼啊。"
    },
    {
      "ja": "角に打ち付けると、殻が卵液に入り込んでしまいますからね",
      "zh": "在尖角上敲的話,蛋殼會掉進蛋液裡啊。"
    },
    {
      "ja": "フライパンに油を入れる量が多くて、ご飯がべとべとになっちゃったのよ。",
      "zh": "平底鍋裡油放太多,飯就變得黏答答的。"
    },
    {
      "ja": "焦げるといけないと思ってたくさん入れたんだけど、油ってほんの少しで良いのね。知らなかったわ",
      "zh": "因為怕燒焦放了很多,沒想到油只要一點點就好。我都不知道。"
    },
    {
      "ja": "玉子焼きがどうしても黄色と白のまだらになるのよ。",
      "zh": "煎蛋總是會出現黃白相間的斑紋。"
    },
    {
      "ja": "佳亮くん。……私の話、煩い……？",
      "zh": "佳亮。……我講的話,很煩嗎……?"
    },
    {
      "ja": "薫子さんの話で、煩いことなんて、ありませんよ",
      "zh": "薰子小姐的話,從來不會讓我覺得煩。"
    },
    {
      "ja": "じゃあ、また二週間後。戸締りしっかりしてくださいね",
      "zh": "那麼,兩週後再見。請好好鎖門喔。"
    },
    {
      "ja": "うん、今日もありがとう",
      "zh": "嗯,今天也謝謝你。"
    },
    {
      "ja": "あのね、この前……、あ、ううん、なんでもない",
      "zh": "那個啊,前幾天……啊,不,沒事。"
    },
    {
      "ja": "あ……、すみません、どうぞ",
      "zh": "啊……抱歉,妳請說。"
    },
    {
      "ja": "ううん。大したことじゃないの！",
      "zh": "不,沒什麼大不了的!"
    },
    {
      "ja": "今日は、豆腐ステーキのきのこソース掛けとタコのバター炒めです",
      "zh": "今天是淋上菇類醬汁的豆腐排,還有奶油炒章魚。"
    },
    {
      "ja": "じゃあ",
      "zh": "那麼。"
    },
    {
      "ja": "いただきます",
      "zh": "我要開動了。"
    },
    {
      "ja": "じゃあ、おやすみなさい。戸締り、気を付けて",
      "zh": "那麼,晚安。鎖門小心點。"
    },
    {
      "ja": "うん。今日もありがとう",
      "zh": "嗯。今天也謝謝你。"
    },
    {
      "ja": "恋人が、居ったんや……",
      "zh": "她有戀人啊……"
    },
    {
      "ja": "大事やねん……。薫子さんも、ご飯の時間も……",
      "zh": "對我來說很重要啊……。薰子小姐也是,吃飯的時間也是……"
    },
    {
      "ja": "あの…、なにもなしじゃ寂しいから、コーヒーでもどうかと思って",
      "zh": "那個……什麼都不喝有點冷清,我想說喝杯咖啡如何。"
    },
    {
      "ja": "あの、ね……。私、佳亮くんに、…伝えたいことがあって……",
      "zh": "那個……我有件事,想告訴佳亮……"
    },
    {
      "ja": "薫子さん、一人でオムライス作れるようになるの、夢でしたもんね。",
      "zh": "薰子小姐妳一直夢想著能一個人做出蛋包飯吧。"
    },
    {
      "ja": "良かったです。めっちゃ上手に出来てます",
      "zh": "太好了。做得非常好。"
    },
    {
      "ja": "嘘は要らないわ、佳亮くん。",
      "zh": "不需要說謊話,佳亮。"
    },
    {
      "ja": "私は、どう頑張ってもこんなオムライスしか作れないのよ…。出来損ないの女だわ……",
      "zh": "我再怎麼努力,也只能做出這種蛋包飯……。我是個失敗的女人……"
    },
    {
      "ja": "どうしてですか。最初卵もろくに割れなかった薫子さんが、卵をきれいに割って、それをきれいに混ぜて、挙句の果てに火を使ってお米と卵を炒めたんでしょう？",
      "zh": "怎麼會呢。最初連蛋都打不好的薰子小姐,現在能把蛋打得漂亮、攪拌得均勻,最後還能用火炒米飯和蛋,不是嗎?"
    },
    {
      "ja": "すごい進歩ですよ。いくらでも褒めます",
      "zh": "進步很大喔。我要狠狠地誇妳。"
    },
    {
      "ja": "でも…っ、一人で、作れるように、なった、ら、…食べ、て、くれる、…って、…よし、あきくんが…、言って、…くれた、…から、頑張れた、の……",
      "zh": "可是……佳亮你說過,如果我能一個人做出來,你會吃我做的……我才能一直努力下去的啊……"
    },
    {
      "ja": "ありがとうございます、薫子さん。僕も、薫子さんのお力になれたみたいで、嬉しいです。",
      "zh": "謝謝妳,薰子小姐。我也很開心,似乎能成為薰子小姐的助力。"
    },
    {
      "ja": "…これ、崩してまうのが勿体ないですけど、いただきますね",
      "zh": "……把它弄碎有點可惜,但我要開動了。"
    },
    {
      "ja": "まって……。……そのオムライス、まだ仕上げてないの……",
      "zh": "等等……。那個蛋包飯,還沒完成……"
    },
    {
      "ja": "好きです……っ",
      "zh": "我喜歡你……"
    },
    {
      "ja": "こんな、女の屑みたいな私だけど、好きな気持ちは、本当なの……。",
      "zh": "雖然我是這樣不如人的女人,但喜歡你的心情,是真的……"
    },
    {
      "ja": "料理教室を逆手に取るようなことしてごめんなさい。",
      "zh": "利用料理教室達到目的,對不起。"
    },
    {
      "ja": "…でも、あれがないと、佳亮くんに会えなかったから……",
      "zh": "……但是,沒有那個的話,我就見不到佳亮了……"
    },
    {
      "ja": "気持ちを伝えられただけで、満足だわ…。今後は…、…佳亮くんと彼女の邪魔はしない",
      "zh": "光是能傳達心意,我就滿足了……。今後……我不會妨礙佳亮和你女朋友的。"
    },
    {
      "ja": "薫子さんには恋人がいますよね？　その方はどうしたんですか？",
      "zh": "薰子小姐妳有戀人對吧?那個人怎麼了?"
    },
    {
      "ja": "それに、僕の彼女って？",
      "zh": "還有,我的女朋友是?"
    },
    {
      "ja": "そう、恋人！　この前、ランボルギーニで帰ってきた薫子さんとキスをしてたでしょう！",
      "zh": "對,戀人!之前坐藍寶堅尼回來的薰子小姐還跟對方接吻了吧!"
    },
    {
      "ja": "ランボルギーニ…？　兄のことかしら…",
      "zh": "藍寶堅尼……?是說我哥哥嗎……?"
    },
    {
      "ja": "お…っ、お兄さんとキスしたりするんですかっ!?",
      "zh": "妳、妳會和哥哥接吻嗎!?"
    },
    {
      "ja": "するわ。家族ならするものじゃないの？",
      "zh": "會啊。家人之間不是都會這樣嗎?"
    },
    {
      "ja": "それで…、…彼女の居る佳亮くんに聞くのは、変かもしれないけれど…、佳亮くんは、私のことを、どう思っているのか、…聞いても良いのかしら……",
      "zh": "那麼……問有女朋友的佳亮可能很奇怪,但是……佳亮你是怎麼看我的,我可以問嗎……?"
    },
    {
      "ja": "この展開で、言わなきゃ分かりませんかね？",
      "zh": "都到這個地步了,還不講就不懂嗎?"
    },
    {
      "ja": "大事なことは、言葉にしないと伝わらないわ",
      "zh": "重要的事情,不化作言語就傳達不了。"
    },
    {
      "ja": "だから私は言葉にしたのよ",
      "zh": "所以我才把它說出口了。"
    },
    {
      "ja": "…世界で一番美味しいオムライスですよ",
      "zh": "……是世界上最好吃的蛋包飯喔。"
    },
    {
      "ja": "薫子、何度言ったら分かるんだ。",
      "zh": "薰子,我說過多少遍妳才懂啊。"
    },
    {
      "ja": "私は嫁入り修行をしろとは言ったが、それはそんなことでではない。",
      "zh": "我是叫妳做嫁妝修行,但不是這種事。"
    },
    {
      "ja": "大体、大瀧の娘が料理なんかする必要はない",
      "zh": "說到底,大瀧家的女兒沒必要做菜。"
    },
    {
      "ja": "本当にそうよ、薫子。お父様の言う通り。手に怪我が絶えないじゃない。",
      "zh": "真的就是這樣,薰子。父親說的對。妳手上的傷沒斷過啊。"
    },
    {
      "ja": "もっと自分の身体を大事にして",
      "zh": "更愛惜自己的身體吧。"
    },
    {
      "ja": "まあまあ、父さん母さん。薫子は昔から好奇心旺盛だったし、やってみたいと思ったことを曲げるような子じゃなかっただろう？",
      "zh": "好啦好啦,爸爸媽媽。薰子從以前就好奇心旺盛,想做的事不會被人左右的,不是嗎?"
    },
    {
      "ja": "今は怪我が絶えないけど、そのうち上手になるよ。薫子は努力家だからね",
      "zh": "現在傷雖然沒斷過,但很快就會熟練的。薰子很努力嘛。"
    },
    {
      "ja": "樹は何時も薫子の肩ばかり持つのね",
      "zh": "樹總是站在薰子那邊呢。"
    },
    {
      "ja": "妹が可愛いからね",
      "zh": "因為妹妹很可愛嘛。"
    },
    {
      "ja": "兄さん、ごめんなさい。兄さんには何時も迷惑かけちゃうわね",
      "zh": "哥哥,對不起。我總是給哥哥添麻煩呢。"
    },
    {
      "ja": "何を言うんだ、薫子。愛しい妹が挑戦しようとしていることを、俺が応援しないわけがないだろう？",
      "zh": "妳在說什麼,薰子。可愛的妹妹想挑戰的事,我怎麼可能不支持呢?"
    },
    {
      "ja": "心配ないよ",
      "zh": "別擔心。"
    },
    {
      "ja": "それに、父さんも母さんも薫子が心配なだけで、本気で反対しているわけじゃないよ。",
      "zh": "而且,爸爸媽媽只是擔心薰子,並不是真的反對。"
    },
    {
      "ja": "もし本気だったら、お前の一人暮らしだって認めないだろう？",
      "zh": "如果真的反對,連妳自己住都不會允許吧?"
    },
    {
      "ja": "母さんの心配は、俺は少しわかる。きれいな手が傷だらけじゃないか。もっと身体を大事にしてくれよ",
      "zh": "媽媽的擔心我也有一點懂。漂亮的手都是傷,更愛惜自己的身體吧。"
    },
    {
      "ja": "兄さん…。兄さんは、私がすることを愚かだと思う？",
      "zh": "哥哥……哥哥覺得我做的事很愚蠢嗎?"
    },
    {
      "ja": "まさか。薫子が何事にもまじめで熱心だということは、俺は良く知っているよ。",
      "zh": "怎麼會。薰子做什麼事都認真又熱心,我很清楚。"
    },
    {
      "ja": "急に料理を習い始めた理由も、あるんだろう？",
      "zh": "突然開始學料理,也有理由的吧?"
    },
    {
      "ja": "……好きな、…ひとが、居るの……",
      "zh": "……我有……喜歡的人……"
    },
    {
      "ja": "とても素敵で、…料理の上手な人なの…。",
      "zh": "是個非常棒、會做菜的人……"
    },
    {
      "ja": "いろいろな料理を食べさせてくれて、本当にやさしい人なの…。",
      "zh": "他做各種料理給我吃,是個真的很溫柔的人……"
    },
    {
      "ja": "恋人が居るんだけど、…気持ちを伝えたくて……",
      "zh": "他有女朋友,但是……我想把心意告訴他……"
    },
    {
      "ja": "それで、オムライスを作って彼にご馳走しようというんだね？",
      "zh": "所以妳才想做蛋包飯請他吃對吧?"
    },
    {
      "ja": "告白したら、家に戻るわ。…あの部屋は、彼に近すぎるから",
      "zh": "告白之後,我就回家。……那個房間,離他太近了。"
    },
    {
      "ja": "彼が悪いわけじゃないわ。私が一人で落ち込んでいただけ。",
      "zh": "他沒有錯。是我一個人沮喪而已。"
    },
    {
      "ja": "でも、前向きになれたのも、彼のおかげなのよ",
      "zh": "但是,我能變得積極,也是多虧了他。"
    },
    {
      "ja": "わかるよ、白樺から聞いた。良い人のようだね",
      "zh": "我懂的,我聽白樺說了。似乎是個好人呢。"
    },
    {
      "ja": "そう。とてもいいひと",
      "zh": "對。非常好的人。"
    },
    {
      "ja": "彼を、…困らせてしまうわね…",
      "zh": "我會讓他為難吧……"
    },
    {
      "ja": "そんなことないさ",
      "zh": "才不會呢。"
    },
    {
      "ja": "彼は分かってくれるよ。薫子の気持ちも、告白の理由も",
      "zh": "他會理解的。薰子的心情,還有告白的理由。"
    },
    {
      "ja": "そうだと、嬉しいわ…",
      "zh": "如果真是這樣就好了……"
    },
    {
      "ja": "いらっしゃい、杉山くん。初めまして、大瀧さん",
      "zh": "歡迎光臨,杉山。初次見面,大瀧小姐。"
    },
    {
      "ja": "まあ、座って。お茶でも出すわ",
      "zh": "來,坐吧。我泡杯茶。"
    },
    {
      "ja": "あ、ありがとう、佳亮くん……",
      "zh": "啊,謝謝你,佳亮……"
    },
    {
      "ja": "ふふ、いきなり他人の家では緊張しますよね",
      "zh": "呵呵,突然到別人家會緊張的吧。"
    },
    {
      "ja": "それで、織畑さん。用事と言うのは…",
      "zh": "那麼,織畑小姐,您說的事情是……?"
    },
    {
      "ja": "以前、大瀧さんに誤解させた杉山くんとのお弁当ランチ、あれ、佐倉くんのご両親とのお食事会で出すお料理を見てもらっていたのよ。",
      "zh": "之前讓大瀧小姐誤會的我跟杉山一起吃便當的事,其實是我請他看看要在跟佐倉家父母聚餐時端出的料理。"
    },
    {
      "ja": "その節はごめんなさいね、大瀧さん",
      "zh": "當時真是抱歉啊,大瀧小姐。"
    },
    {
      "ja": "おかげで印象もよく受け入れてもらえたわ。婚約したの",
      "zh": "多虧如此,印象很好被接受了。我們訂婚了。"
    },
    {
      "ja": "男の人はどうだか分からないけど、女は彼女かもって疑った相手が実のところどうなのかって、気になるもんだから、大瀧さんの誤解を徹底的に解消しておきたくて…",
      "zh": "男生我不曉得,但女生若是懷疑對方是不是「他女朋友」,就會很在意那實際是怎麼一回事,所以我想徹底解開大瀧小姐的誤會……"
    },
    {
      "ja": "薫子さん、何でも自分で決めて片付けちゃうんで、そういう機微は分からないから助かります",
      "zh": "薰子小姐什麼事都自己決定處理,所以不懂這種微妙之處,妳這樣幫忙真是太好了。"
    },
    {
      "ja": "女心は複雑よね",
      "zh": "女人心很複雜的呢。"
    },
    {
      "ja": "薫子さん、栗好きですか？",
      "zh": "薰子小姐喜歡栗子嗎?"
    },
    {
      "ja": "じゃあ、時期になったら栗ご飯でもやりましょうか",
      "zh": "那麼,等到了季節做栗子飯吧。"
    },
    {
      "ja": "良いわね。手伝わせて",
      "zh": "好啊。讓我幫忙吧。"
    },
    {
      "ja": "良いですね。二人で作りましょう",
      "zh": "好啊。我們兩個一起做。"
    },
    {
      "ja": "楽しめましたか？",
      "zh": "玩得開心嗎?"
    },
    {
      "ja": "うん、楽しめたわ。私、家を出てから会社の人としか交友がなかったから、新しい知り合いが出来て嬉しい",
      "zh": "嗯,很開心。我自從離家後就只跟公司的人有來往,所以能認識新朋友很開心。"
    },
    {
      "ja": "…私も何時か…、佳亮くんのご両親に、お料理振舞わなきゃいけないのかしら…",
      "zh": "……我哪天也得……為佳亮的父母做料理嗎……?"
    },
    {
      "ja": "まだ先のことなので心配要りませんが、両親は僕のことよく分かってますし、薫子さんのこともきっと良く分かってくれます",
      "zh": "那是以後的事不必擔心,我父母很了解我,也一定會好好認識薰子小姐妳的。"
    },
    {
      "ja": "そうだと良いけど…",
      "zh": "希望是這樣……"
    },
    {
      "ja": "それより、僕のほうが問題ですよ",
      "zh": "比起這個,我自己才是個問題啊。"
    },
    {
      "ja": "あんなお屋敷に住んではる薫子さんのご両親に、僕が受け入れてもらえるかどうかの方ですよ",
      "zh": "是住在那麼大宅邸的薰子小姐的父母,願不願意接受我才對。"
    },
    {
      "ja": "大問題だなあ…",
      "zh": "是個大問題啊……"
    },
    {
      "ja": "私も両親を納得させるわ",
      "zh": "我也會說服我父母的。"
    },
    {
      "ja": "薫子さんは、僕と一緒に行きたいところってありますか？",
      "zh": "薰子小姐,有沒有想跟我一起去的地方?"
    },
    {
      "ja": "す、好きなこととか…。何かあれば……",
      "zh": "妳、妳喜歡的事情之類的……有什麼的話……"
    },
    {
      "ja": "…そうね、運転は好きだわ。最近してなかったけど、前は遠くまで走ったりしてたなあ",
      "zh": "……我想想,我喜歡開車。最近沒開,但以前會開到很遠的地方呢。"
    },
    {
      "ja": "…じゃあ、紅葉狩りに行きませんか。僕、お弁当用意しますよ",
      "zh": "……那麼,要不要去賞楓?我來準備便當。"
    },
    {
      "ja": "じゃあ私が運転するわね。お弁当、楽しみ",
      "zh": "那我來開車吧。便當很期待呢。"
    },
    {
      "ja": "兄さん、助けて",
      "zh": "哥哥,救救我。"
    },
    {
      "ja": "どうしたんだ、薫子",
      "zh": "怎麼了,薰子。"
    },
    {
      "ja": "ど、どうしよう。…佳亮くんに、紅葉狩りに誘われたわ…",
      "zh": "怎、怎麼辦。……佳亮邀我去賞楓……"
    },
    {
      "ja": "私、佳亮くんとお出かけするような洋服を持ってないのよ…",
      "zh": "我,沒有跟佳亮出去玩會穿的衣服啊……"
    },
    {
      "ja": "なんだ、そんなことか。俺に任せておけ",
      "zh": "什麼嘛,就這種事啊。交給我吧。"
    },
    {
      "ja": "それにしても、心許ないわ…",
      "zh": "話雖如此,還是很沒把握啊……"
    },
    {
      "ja": "…こんなに張り切ってしまって、佳亮くんが見たらどう思うかしら…",
      "zh": "……打扮成這樣,佳亮看到會怎麼想呢……"
    },
    {
      "ja": "喜んでくれるかしら…",
      "zh": "他會高興嗎……"
    },
    {
      "ja": "……び…、…っくりしました…。薫子さん、スカート持ってはったんですね…",
      "zh": "嚇、嚇了我一跳……。薰子小姐,妳原來有裙子啊……"
    },
    {
      "ja": "素敵です…。…上手に言えませんけど、とても似合ってます",
      "zh": "好棒……。我不太會說,但很適合妳。"
    },
    {
      "ja": "……ありがとう…",
      "zh": "……謝謝……"
    },
    {
      "ja": "張り切って作りました。あとで食べましょうね",
      "zh": "我用心做的。等下一起吃吧。"
    },
    {
      "ja": "そうね、楽しみ！　さあ、乗って",
      "zh": "嗯,好期待!來,上車吧。"
    },
    {
      "ja": "か…っ、薫子さんっ！　待って、待ってください！",
      "zh": "薰、薰子小姐!等等,等一下!"
    },
    {
      "ja": "ひ、…膝が見えてしまいます…",
      "zh": "妳的膝蓋……都露出來了……"
    },
    {
      "ja": "ご……っ、ごめんなさい……っ！",
      "zh": "對、對不起……!"
    },
    {
      "ja": "い、…いえ、…薫子さんは、悪くないです…。僕こそ、…あの、…すみません……",
      "zh": "不、不,薰子小姐妳沒有錯……。是我才該……那個……抱歉……"
    },
    {
      "ja": "…下手に繕うと、良いことないわね。…佳亮くん、カーディガン借りるわ",
      "zh": "……硬要掩飾也沒什麼好處。……佳亮,我借你的開襟衫一下。"
    },
    {
      "ja": "カッコいいよなあ、薫子さん…。女の人やったら軽とかが多い筈やのに、こんな大きな車…",
      "zh": "好帥啊,薰子小姐……。女生開的應該都是輕型車吧,卻開這種大車……"
    },
    {
      "ja": "兄さん…っ",
      "zh": "哥哥……!"
    },
    {
      "ja": "兄さん、…私やっぱり駄目よ",
      "zh": "哥哥,……我果然不行啊。"
    },
    {
      "ja": "うわあ、あの娘（こ）、男の出したお弁当食べてる",
      "zh": "哇,那女生,在吃男生做的便當耶。"
    },
    {
      "ja": "おい、女の方がデカいぞ",
      "zh": "喂,女的比較大隻耶。"
    },
    {
      "ja": "男の方も、なよっちい顔してんね",
      "zh": "男的長得也好娘娘腔。"
    },
    {
      "ja": "気にしない方が良いです。…それに、折角宇綺麗に着てくれたワンピースに似合いません",
      "zh": "別放在心上比較好。……再說,跟妳難得穿得這麼漂亮的洋裝不搭。"
    },
    {
      "ja": "僕が童顔で頼りないのは本当ですし",
      "zh": "我長著一張娃娃臉、看起來不可靠也是事實啊。"
    },
    {
      "ja": "私が料理上手で背が低かったら、佳亮くんにあんな顔させなかったのかしら…",
      "zh": "如果我廚藝好又身高矮的話,就不會讓佳亮露出那種表情了吧……"
    },
    {
      "ja": "私の所為で、佳亮くんを傷付けた…",
      "zh": "因為我,傷害了佳亮……"
    },
    {
      "ja": "…お別れした方が良いのかな……",
      "zh": "……是不是分手比較好呢……"
    },
    {
      "ja": "実は、通りすがりの人に嫌なことを言われて、佳亮くんを傷付けてしまったんです。どうしたら佳亮くんに謝れるでしょうか？",
      "zh": "其實,我被路過的人說了難聽的話,傷害到了佳亮。我該怎麼向佳亮道歉呢?"
    },
    {
      "ja": "通りすがりの人の言うことなんて、気にすることないですよ。",
      "zh": "路人說的話,沒必要在意。"
    },
    {
      "ja": "杉山くんも、きっと気にしてないと思うな。むしろ杉山くんは、大瀧さんのことを気にしてると思います",
      "zh": "杉山一定也不在意吧。反而我覺得杉山是在意大瀧小姐妳。"
    },
    {
      "ja": "大瀧さんが自分の誇りと、杉山くんの名誉の為に立ち上がったのに、杉山くんは止めたんでしょう？　大瀧さんのプライドを傷付けたと思ってるんじゃないかな",
      "zh": "大瀧小姐為了自己的尊嚴和杉山的名譽挺身而出,杉山卻阻止妳吧?他大概覺得傷到大瀧小姐的自尊了。"
    },
    {
      "ja": "私は佳亮くんに似合わないんじゃないかと思うんです。背も高いし、女らしくないし、喧嘩っ早いし",
      "zh": "我覺得自己跟佳亮不相配。又高、又不像女人、又容易動氣。"
    },
    {
      "ja": "そういう基準で杉山くんは見てないんじゃないかな。",
      "zh": "我覺得杉山不是用那種標準在看的吧。"
    },
    {
      "ja": "大瀧さんが女らしくないって気にするってことは、杉山くんが料理が得意なのを男らしくないって思うことと同じよ。",
      "zh": "大瀧小姐在意自己不像女人,就跟杉山覺得自己擅長料理不像男人是一樣的喔。"
    },
    {
      "ja": "カッコいい大瀧さんとかわいい杉山くん、私たちが見ても素敵なカップルだったわ。",
      "zh": "帥氣的大瀧小姐和可愛的杉山,在我們看來也是很棒的一對。"
    },
    {
      "ja": "お互いに出来ない所を補い合える、理想の二人よ",
      "zh": "彼此互補各自不擅長的地方,是理想的兩人喔。"
    },
    {
      "ja": "あとは杉山くんとちゃんと話せると良いですね。",
      "zh": "接下來能好好跟杉山談談就好了呢。"
    },
    {
      "ja": "一人でしこりを抱えたままだと、杉山くんも辛いと思うわ",
      "zh": "如果妳獨自悶在心裡,杉山也會難過的。"
    },
    {
      "ja": "私、明日の朝、部屋に帰るわ",
      "zh": "我明天早上要回房間。"
    },
    {
      "ja": "もう良いのか？",
      "zh": "已經沒事了嗎?"
    },
    {
      "ja": "うん。佳亮くんと話してみる",
      "zh": "嗯。我會試著跟佳亮談談。"
    },
    {
      "ja": "薫子が良いと思う方法なら、俺は全力で応援する。",
      "zh": "薰子覺得好的方法,我都全力支持。"
    },
    {
      "ja": "でも、辛くなったら帰ってこい。俺は何時でも此処に居る",
      "zh": "但是,難過的時候就回來。我隨時都在這裡。"
    },
    {
      "ja": "ありがとう、兄さん",
      "zh": "謝謝你,哥哥。"
    },
    {
      "ja": "お互いに「相手が、相手が」ってそればっかり。",
      "zh": "你們兩個都只想著「對方、對方」。"
    },
    {
      "ja": "噛み合ってるうちは良いけど、すれ違ったら大変よ。気を付けなさい",
      "zh": "彼此契合的時候還好,一旦錯位就很麻煩了。要小心點。"
    },
    {
      "ja": "佳亮くんが会ってくれるって言ってくれて、嬉しかったわ",
      "zh": "你說願意見我,我很高興。"
    },
    {
      "ja": "僕も、昨日は絶対薫子さんが怒ってはったと思うてたから…",
      "zh": "我也是,昨天確定薰子小姐妳一定生氣了……"
    },
    {
      "ja": "栗ご飯にしようと思うんです",
      "zh": "我想做栗子飯。"
    },
    {
      "ja": "新婚さん。今日は秋刀魚を安くしとくよ、買ってって～",
      "zh": "新婚夫妻。今天秋刀魚算便宜的喔,買回去吧——"
    },
    {
      "ja": "いや～、初々しい反応だねえ～。きっと秋刀魚が美味しいよ！　ほら買った買った！",
      "zh": "啊呀——好生澀的反應啊——秋刀魚一定很好吃!來,買回去買回去!"
    },
    {
      "ja": "ああ、頂きます！　だからそんな風に言わないでください！",
      "zh": "啊,我買!所以拜託別那樣說!"
    },
    {
      "ja": "美味しいご飯の夢が見れそうじゃない",
      "zh": "感覺能夢到好吃的飯呢。"
    },
    {
      "ja": "ん、わ～、さっぱりしてる！　これ、幾らでも食べられそうよ！　日本酒、合うわあ",
      "zh": "嗯,哇——好清爽!這個,感覺可以吃個不停!跟日本酒好搭啊。"
    },
    {
      "ja": "それは良かったです。沢山作ったので、沢山食べて下さいね",
      "zh": "那真是太好了。我做了很多,請多吃點喔。"
    },
    {
      "ja": "あ～、やっぱり佳亮くんと一緒に飲みたい！　飲めたら良いのにね～",
      "zh": "啊——果然好想跟佳亮一起喝!如果你會喝就好了——"
    },
    {
      "ja": "アレルギーやと思て、諦めて下さい。気持ち悪くなるだけなんで",
      "zh": "請當作我有過敏死了這條心吧。我喝了只會覺得噁心而已。"
    },
    {
      "ja": "うう～ん…。一緒にご飯食べてるのに、一緒に飲めないのは寂しいわ…",
      "zh": "嗯——……一起吃飯卻不能一起喝酒,好寂寞啊……"
    },
    {
      "ja": "杉山くん、クリスマス会に参加しない？",
      "zh": "杉山,要不要參加聖誕派對?"
    },
    {
      "ja": "杉山くんは大瀧さんと結婚は考えてないの？　会社の面子に顔見せしておくと良いわよ",
      "zh": "杉山你沒考慮跟大瀧小姐結婚嗎?在公司同事面前露露臉比較好喔。"
    },
    {
      "ja": "年上の女性を待たせるもんじゃないわ。大瀧さんが気にしてたらどうするのよ",
      "zh": "不該讓年長女性等的喔。大瀧小姐要是介意了怎麼辦?"
    },
    {
      "ja": "薫子さんには隠し事が出来へんなあ。",
      "zh": "對薰子小姐沒辦法隱瞞事情啊。"
    },
    {
      "ja": "……薫子さん、クリスマスの週、何か予定ありますか？",
      "zh": "薰子小姐,聖誕節那週有什麼計畫嗎?"
    },
    {
      "ja": "二十三日は毎年会社の子とクリスマス会をするの。",
      "zh": "二十三號每年都跟公司同事辦聖誕派對。"
    },
    {
      "ja": "クリスマスイヴは、ほら、うちの会社女性が多いでしょう。空けてあげないと可哀想だから",
      "zh": "聖誕夜嘛,我們公司女性多,不空出來讓她們陪家人會很可憐。"
    },
    {
      "ja": "私なんかが行っても良いのかしら",
      "zh": "像我這樣的人去也可以嗎?"
    },
    {
      "ja": "佐倉さんも参加されるの？　それじゃあ、勇気を出して行ってみようかしら",
      "zh": "佐倉先生也參加嗎?那麼,我就鼓起勇氣去看看吧。"
    },
    {
      "ja": "お前クリスマス会に参加するんだって？",
      "zh": "聽說你要參加聖誕派對啊?"
    },
    {
      "ja": "しかも彼女連れてくるらしいじゃん？",
      "zh": "而且還要帶女朋友來啊?"
    },
    {
      "ja": "弁当男子、女には興味なかったんじゃないのかよ",
      "zh": "便當男子,你不是對女生沒興趣嗎?"
    },
    {
      "ja": "案外むっつりだったんだな",
      "zh": "意外地原來是悶騷啊。"
    },
    {
      "ja": "どういう感じの女なんだよ、教えろよ",
      "zh": "是什麼樣的女生,告訴我們吧。"
    },
    {
      "ja": "そんなの敢えて俺から言わんでも、会えばわかるやろ",
      "zh": "那種事我不特意說,見了就知道吧。"
    },
    {
      "ja": "このワンピースも紅葉狩りの時と一緒で兄に見繕ってもらったのよ。自分じゃ全然分からないから",
      "zh": "這件洋裝跟賞楓那次一樣,是哥哥幫我挑的。我自己完全不懂。"
    },
    {
      "ja": "ありがとう。佳亮くんも何時もの雰囲気と違うわね。その紺のシャツ、とても素敵だわ",
      "zh": "謝謝。佳亮跟平常的氣氛也不一樣呢。那件深藍襯衫,非常好看。"
    },
    {
      "ja": "あ、ありがとうございます……",
      "zh": "啊,謝謝……"
    },
    {
      "ja": "じゃあ、行きましょうか",
      "zh": "那麼,我們走吧。"
    },
    {
      "ja": "あ、杉山くん。大瀧さんも",
      "zh": "啊,杉山。還有大瀧小姐。"
    },
    {
      "ja": "来てくれてありがとう。楽しんで行ってね",
      "zh": "謝謝你們來。請好好享受喔。"
    },
    {
      "ja": "はるかさんにお会いできてうれしいです。またあとでお話してください",
      "zh": "能見到遙小姐很高興。等等再請您聊聊。"
    },
    {
      "ja": "薫子さんのおうちのご飯には敵わないと思いますが、作ろうと思ったら作れますよ。リクエストがあったら言ってください",
      "zh": "我比不上薰子小姐家裡的飯,但只要想做就做得出來。有什麼要求請告訴我。"
    },
    {
      "ja": "私、佳亮くんの作ってくれるお料理好きよ。やさしい味がするわ",
      "zh": "我喜歡佳亮做的料理喔。是溫柔的味道。"
    },
    {
      "ja": "ただの家庭料理ですけどね",
      "zh": "只是普通的家常菜罷了。"
    },
    {
      "ja": "謙遜しちゃ駄目",
      "zh": "不可以謙虛。"
    },
    {
      "ja": "私は母親の作った料理を食べたことがないから、家庭料理っていうものに憧れがあったのよ。",
      "zh": "我沒吃過母親做的料理,所以一直很嚮往家常菜這種東西。"
    },
    {
      "ja": "お弁当もそう。何時も平田が作ってくれてたけど、学校の友達はみんなお母さまが手作りされてて、羨ましかったわ。",
      "zh": "便當也是。雖然平田一直幫我做,但學校的朋友都是母親親手做的,我很羨慕。"
    },
    {
      "ja": "勿論平田の料理が好きじゃないわけじゃないけど、平田は大瀧に雇われてるから私に食事を作ってくれるだけだし、やっぱり『この人の為』っていう感情は違うでしょう？",
      "zh": "我當然不是不喜歡平田的料理,但平田是大瀧家僱用的,只是為我做飯,「為了這個人」的那種感情果然還是不同吧?"
    },
    {
      "ja": "僕のご飯で良ければ、いくらでも食べてください",
      "zh": "我的飯如果可以的話,妳要吃多少都行。"
    },
    {
      "ja": "そうね。でもたまにはこうやって外で食べるのも悪くないわ。いつも佳亮くんに作らせてばかりだから",
      "zh": "說得也是。但偶爾這樣外出吃飯也不錯。一直都讓佳亮做飯嘛。"
    },
    {
      "ja": "杉山。やっと来たなら、彼女紹介してくんなきゃ",
      "zh": "杉山。終於來了,得介紹一下女朋友吧。"
    },
    {
      "ja": "自分だけ楽しんでんなよ",
      "zh": "別只顧著自己享受啊。"
    },
    {
      "ja": "大瀧薫子と言います。杉山くんにはいつも親切にしていただいています。ご同僚の方ですか？",
      "zh": "我叫大瀧薰子。杉山一直很照顧我。是同事嗎?"
    },
    {
      "ja": "私、辛い物も平気だから、これは当たっても大丈夫だわ",
      "zh": "我吃辣不怕,所以中了也沒事。"
    },
    {
      "ja": "かっら!!",
      "zh": "好辣!!"
    },
    {
      "ja": "げほ……っ！　ごほん、ごほん！",
      "zh": "咳……!咳咳!"
    },
    {
      "ja": "佳亮くん、チゲ鍋、大丈夫？",
      "zh": "佳亮,豆腐鍋你應付得來嗎?"
    },
    {
      "ja": "そうね。でも佳亮くんがそんなに辛いなら、グラスを変えてあげればよかった",
      "zh": "也對。但既然佳亮這麼怕辣,當初換杯子給你就好了。"
    },
    {
      "ja": "佳亮くん、甘いものはどう？　少しは辛いのと中和されないかな？",
      "zh": "佳亮,吃點甜的怎麼樣?可以稍微中和辣味吧?"
    },
    {
      "ja": "佳亮くん、良いものをもらっちゃったわ。ホットプレートよ、これ",
      "zh": "佳亮,我拿到好東西了。這是電烤盤喔。"
    },
    {
      "ja": "これから寒いですし、テーブルの上で焼き立てを食べられるメニューを考えますよ。",
      "zh": "之後會變冷,我會想些可以在桌上現烤現吃的菜單。"
    },
    {
      "ja": "ちょっと電車で持って帰るには大きいわね。私帰りにタクシーを拾うわ。佳亮くん、一緒に乗って帰りましょ",
      "zh": "搭電車帶回去有點太大了。我回程攔計程車吧。佳亮,一起搭吧。"
    },
    {
      "ja": "ハバネロには当たっちゃうし、ビンゴは当たらないし、良いことなかったなあ……",
      "zh": "哈瓦那辣椒中獎了,賓果卻沒中,真沒什麼好事啊……"
    },
    {
      "ja": "私ばっかり楽しんでごめんなさい",
      "zh": "只有我自己玩得開心,對不起。"
    },
    {
      "ja": "酔っ払いも多いと思うので、気を付けてくださいね",
      "zh": "醉漢應該很多,請小心喔。"
    },
    {
      "ja": "大丈夫よ。お話終わったら出て来てね",
      "zh": "沒事的。聊完了就出來吧。"
    },
    {
      "ja": "薫子さん",
      "zh": "薰子小姐。"
    },
    {
      "ja": "望月さん……",
      "zh": "望月先生……"
    },
    {
      "ja": "どうして約束を破ったんですか。僕との約束より、大事な用事ですか",
      "zh": "為什麼妳要違背約定?有比跟我的約定更重要的事嗎?"
    },
    {
      "ja": "兄からお伝えしてあった筈です。",
      "zh": "我哥哥應該已經跟您說過了。"
    },
    {
      "ja": "そもそもお約束も、最初に聞いたときにちゃんとお断りしてる筈です。",
      "zh": "再者,那個約定我一開始聽到時就應該已經拒絕了。"
    },
    {
      "ja": "私が今日何処で何をしようと、私の勝手です",
      "zh": "我今天在哪裡做什麼,是我的自由。"
    },
    {
      "ja": "婚約者の誕生日パーティーに出席しないのは、どうかと思います",
      "zh": "不出席未婚妻的生日派對,我覺得不太好。"
    },
    {
      "ja": "婚約のお話も、既にお断りしている筈です",
      "zh": "婚約之事,也應該已經拒絕了。"
    },
    {
      "ja": "僕は認めていない",
      "zh": "我不承認。"
    },
    {
      "ja": "まだパーティーに間に合う。今から戻りましょう",
      "zh": "派對還來得及。現在回去吧。"
    },
    {
      "ja": "薫子さん！",
      "zh": "薰子小姐!"
    },
    {
      "ja": "け、喧嘩は止めてください！　薫子さん、大丈夫ですか!?",
      "zh": "別、別吵架!薰子小姐,妳沒事吧?!"
    },
    {
      "ja": "なんだ、お前は",
      "zh": "你算什麼東西?"
    },
    {
      "ja": "私の大切な人です。乱暴にしないで",
      "zh": "他是我重要的人。請別動粗。"
    },
    {
      "ja": "正気ですか!?　薫子さん！　どこの会社の男ですか！",
      "zh": "妳清醒嗎!?薰子小姐!他是哪家公司的男人!"
    },
    {
      "ja": "会社は関係ありません。私個人の、大切な人です",
      "zh": "跟公司無關。是我個人重要的人。"
    },
    {
      "ja": "薫子さん、そして貴方も。こんなところで喧嘩は駄目です。話し合いで……",
      "zh": "薰子小姐,還有您。在這種地方吵架不好。要好好談談……"
    },
    {
      "ja": "杉山、どうしたんだ",
      "zh": "杉山,怎麼了?"
    },
    {
      "ja": "やけにギャラリーが多いぞ。なにしたんだ",
      "zh": "圍觀的人怎麼這麼多。你做了什麼?"
    },
    {
      "ja": "何が起こったんだい、杉山くん",
      "zh": "發生什麼事了,杉山?"
    },
    {
      "ja": "大瀧さん、大丈夫？",
      "zh": "大瀧小姐,沒事吧?"
    },
    {
      "ja": "薫子さん。今日は諦めますが、婚約の件、僕は諦めませんからね。会長とお父さまにもお話しておきます",
      "zh": "薰子小姐。今天我放棄,但婚約的事我不會放棄的。我會去跟會長和令尊談。"
    },
    {
      "ja": "ホットプレート、傷んじゃったかしら",
      "zh": "電烤盤,壞掉了嗎?"
    },
    {
      "ja": "みっともないところを見せちゃったわね",
      "zh": "讓你看到不堪的一面了呢。"
    },
    {
      "ja": "そんなことないですよ。それより薫子さんに怪我がなくて良かった。……柔道、されてはったんですか？",
      "zh": "才沒這回事。比起這個,薰子小姐妳沒受傷真是太好了。……妳練過柔道嗎?"
    },
    {
      "ja": "護身用にね",
      "zh": "為了防身嘛。"
    },
    {
      "ja": "……僕たち、そういえばお互いの家族の事、話したことなかったですね",
      "zh": "……說起來,我們從沒談過彼此的家人呢。"
    },
    {
      "ja": "先刻の人は望月佑（もちづきたすく）さんと言って、家が決めていた婚約者よ",
      "zh": "剛剛那個人叫望月佑,是家裡定下的未婚夫。"
    },
    {
      "ja": "おうちのお仕事に絡むお話なんですか……？",
      "zh": "是和家族事業有關的事嗎……?"
    },
    {
      "ja": "大瀧建設というの",
      "zh": "叫大瀧建設。"
    },
    {
      "ja": "佳亮くん……",
      "zh": "佳亮……"
    },
    {
      "ja": "……佳亮くんも、私を看板で見る……？",
      "zh": "……佳亮你也用招牌的眼光看我嗎……?"
    },
    {
      "ja": "折角のクリスマスやのに、雰囲気台無しですみません",
      "zh": "難得的聖誕節,氣氛被我毀了,對不起。"
    },
    {
      "ja": "チーズが溶けましたから、もうええと思いますよ",
      "zh": "起司融化了,可以吃了喔。"
    },
    {
      "ja": "家でチーズタッカルビが食べられるなんて嬉しい！",
      "zh": "在家就能吃到起司辣炒雞,好開心!"
    },
    {
      "ja": "うん！　美味しいわ！　ビールがまた合うわね～、進んじゃう",
      "zh": "嗯!好吃!配啤酒又超搭——一直喝個不停。"
    },
    {
      "ja": "今日はほどほどにしておかないと。明日も仕事があることですし",
      "zh": "今天得適可而止才行。明天還要上班。"
    },
    {
      "ja": "うん、でももう一本だけ！",
      "zh": "嗯,但是再來一瓶就好!"
    },
    {
      "ja": "あの、薫子さん。本当はちゃんとしたお店で渡したかったんですけど……",
      "zh": "那個,薰子小姐。其實本來想在正式的店裡交給妳的……"
    },
    {
      "ja": "……やだ。私全然何も用意してないわ",
      "zh": "……不會吧。我完全沒有準備什麼。"
    },
    {
      "ja": "気にしないでください。僕が、あの、あげたかっただけなので……",
      "zh": "請別在意。是我那個,只是想送妳而已……"
    },
    {
      "ja": "わ、素敵",
      "zh": "哇,好棒。"
    },
    {
      "ja": "薫子さんが欲しいものって分からなくて。でもアクセサリーなら持っていても損じゃないかなと思って",
      "zh": "我不知道薰子小姐想要什麼。但飾品的話,拿來放著也不會吃虧吧。"
    },
    {
      "ja": "着けてみても良い？",
      "zh": "可以戴戴看嗎?"
    },
    {
      "ja": "素敵ね。私、あんまりアクセサリーって着けないんだけど、会社に着けて行っても良いかしら",
      "zh": "好美啊。我不太戴飾品的,可以戴去公司嗎?"
    },
    {
      "ja": "もう薫子さんのものなので、自由に着けてください",
      "zh": "已經是薰子小姐的東西了,請隨意佩戴。"
    },
    {
      "ja": "……実は、本当はですね……",
      "zh": "……其實啊,真要說的話……"
    },
    {
      "ja": "今日、お店を予約してたんです。……クリスマスイブだからと思って",
      "zh": "今天,我有訂餐廳。……想說是聖誕夜嘛。"
    },
    {
      "ja": "でもこの前薫子さん、自分のことを『看板』って言わはったでしょう？",
      "zh": "但前幾天薰子小姐妳說自己是「招牌」對吧?"
    },
    {
      "ja": "あれがどうしても気になってもうて……。",
      "zh": "我怎麼也忘不了那句話……"
    },
    {
      "ja": "僕は、先刻みたいに僕の作った料理を美味しいって言うて一緒に食べてくれる薫子さんを好きになったので……、……それはこれからも変わらないってお伝えしたくて、お店はキャンセルしました",
      "zh": "我是因為像剛剛那樣會說我做的料理好吃、一起吃飯的薰子小姐而喜歡上妳的……我想告訴妳這一點以後也不會變,所以取消了餐廳。"
    },
    {
      "ja": "僕にとって、薫子さんは薫子さんなので……。",
      "zh": "對我來說,薰子小姐就是薰子小姐……"
    },
    {
      "ja": "おうちとのことはこれからどうにかしなきゃいけないことですけど、それが理由で好きになったわけでも嫌いになるわけでもないです。",
      "zh": "家族那邊的事是接下來必須解決的,但我不是因為這個喜歡妳,也不會因此討厭妳。"
    },
    {
      "ja": "ありがとう、佳亮くん……。あの時は仕方ないわ。私も情けないところ見せちゃって、ごめんなさい",
      "zh": "謝謝你,佳亮……。那時候也沒辦法。我也讓你看到我難堪的樣子,對不起。"
    },
    {
      "ja": "情けないなんて、そんなこと言わないでください。",
      "zh": "難堪什麼的,請別這麼說。"
    },
    {
      "ja": "強くてカッコいいのは薫子さんの美点ですけど、だからと言って、僕の前でまでそうでなきゃいけないことは、ないです",
      "zh": "堅強帥氣是薰子小姐的優點,但就算這樣,妳在我面前也不必非得這樣不可。"
    },
    {
      "ja": "やっぱりこの部屋に住んでよかった。佳亮くんに会えたもの",
      "zh": "果然搬來這間房間真好。能遇見佳亮。"
    },
    {
      "ja": "佳亮くんは、何時だって私のことを支えてくれてるわ",
      "zh": "佳亮一直以來都在支持我。"
    },
    {
      "ja": "私が私のままで良い、って気付かせてくれたの、佳亮くんが初めてなのよ",
      "zh": "讓我意識到「我可以做我自己」的,佳亮你是第一個。"
    },
    {
      "ja": "なんの御用でしょうか？",
      "zh": "請問有什麼事?"
    },
    {
      "ja": "まず、お詫びをさせてもらいたい。先日はすまなかった。少し取り乱した。",
      "zh": "首先,讓我道歉。前幾天對不起。我有點失態了。"
    },
    {
      "ja": "貴女が本当にあの場所に居るとは思わなかったんだ",
      "zh": "我沒想到妳真的會在那個地方。"
    },
    {
      "ja": "私も大人げなかったです。あんなところで、すみませんでした",
      "zh": "我也是不夠成熟。在那種地方,真是抱歉。"
    },
    {
      "ja": "改めて、誤解を解いておきたい。僕は君のことが好きだ。",
      "zh": "重新請讓我澄清誤會。我喜歡妳。"
    },
    {
      "ja": "僕の心が届いていないのなら、努力をする。何が僕に足りないのか、教えて欲しい",
      "zh": "如果我的心意還沒傳達到,我會努力。請告訴我,我哪裡不足。"
    },
    {
      "ja": "望月さんが足りないということではないんです",
      "zh": "並不是望月先生哪裡不足。"
    },
    {
      "ja": "望月のことを言っているのなら、僕は家を出ても良い。",
      "zh": "如果妳是顧慮望月家的事,我可以離開家族。"
    },
    {
      "ja": "弟に任せれば望月は動くし、弟も優秀だ。僕は個人として貴女と結婚したいと思っている",
      "zh": "交給弟弟的話望月家就能運作,弟弟也很優秀。我是想以個人身分跟妳結婚。"
    },
    {
      "ja": "どうして最初にそう言ってくださらなかったんですか",
      "zh": "您為什麼一開始不這麼說呢?"
    },
    {
      "ja": "お帰りください。もうお話することはありません",
      "zh": "請回吧。沒什麼好談的了。"
    },
    {
      "ja": "佑さん……っ、放してくださいっ",
      "zh": "佑先生……!請放開我!"
    },
    {
      "ja": "嫌だ。君に逃げられるのは嫌だ",
      "zh": "不要。我不要妳逃離我。"
    },
    {
      "ja": "お願いです……。これ以上、嫌いにさせないで……っ",
      "zh": "拜託您……。請別讓我更討厭您……"
    },
    {
      "ja": "そんなにあの男が良いですか……？",
      "zh": "那個男人有那麼好嗎……?"
    },
    {
      "ja": "初めて『私』を好きだと言ってくれた人です……。佑さんは遅かった……",
      "zh": "他是第一個說喜歡「我」這個人的……。佑先生你晚了一步……"
    },
    {
      "ja": "もう、考えを変えることはありませんか……？　本当に……？",
      "zh": "妳真的不會改變想法了嗎……?真的……?"
    },
    {
      "ja": "薫子さん。それでも僕は貴女を諦めないし、貴女は大瀧の看板を背負うことになると思いますよ",
      "zh": "薰子小姐。即使如此我也不會放棄妳,而且妳終究會背負大瀧的招牌的。"
    },
    {
      "ja": "認めたくなくても",
      "zh": "就算妳不願意承認。"
    },
    {
      "ja": "大滝先輩、クッキー焼いたんです。貰ってください",
      "zh": "大瀧學姊,我烤了餅乾。請收下。"
    },
    {
      "ja": "先輩、今日、剣道の練習試合ですよね？　応援に行きます。頑張ってください",
      "zh": "學姊,今天有劍道練習賽對吧?我會去加油。請加油。"
    },
    {
      "ja": "望月くんは何時頃から剣道をやっているの？",
      "zh": "望月你從什麼時候開始練劍道的?"
    },
    {
      "ja": "大滝さんは柔道もやってるんでしょう？　強いんだって聞いたよ",
      "zh": "大瀧妳也練柔道對吧?聽說很強呢。"
    },
    {
      "ja": "そうね、県大会で二位だったわ。優勝出来たらよかったのに",
      "zh": "嗯,縣大會第二名。要是能奪冠就好了。"
    },
    {
      "ja": "だって、自分を守るためには自分がちゃんと強くなきゃ。",
      "zh": "為了保護自己,自己必須夠強才行。"
    },
    {
      "ja": "勝負は嘘をつかないわ。だから私は一番を取りたかったのよ",
      "zh": "勝負是不會說謊的。所以我想拿第一。"
    },
    {
      "ja": "僕も強くなって、一番を取るよ。",
      "zh": "我也會變強,拿到第一的。"
    },
    {
      "ja": "そして僕ら一緒に背中を預けて守り合ったら、怖いものなんて居なくなるんじゃないかな",
      "zh": "如果我們互相託付背後彼此守護,就沒有什麼好怕的了吧。"
    },
    {
      "ja": "今年は葉月が彼氏を紹介するって言うてるから、佳亮もちょっとスケジュール考えといてな",
      "zh": "今年葉月說要介紹男朋友,佳亮你也稍微想想行程喔。"
    },
    {
      "ja": "彼氏の紹介くらいで帰ってられへんよ。婚約と結婚決まったら連絡してや。こっちも忙しいねん",
      "zh": "光是介紹男朋友我可回不去。等訂婚跟結婚定下來再聯絡吧。我這邊也很忙。"
    },
    {
      "ja": "葉月、エエ人見つけたんか",
      "zh": "葉月,妳找到好對象了嗎?"
    },
    {
      "ja": "お兄ちゃんくらいエエ人",
      "zh": "跟哥哥一樣是好人。"
    },
    {
      "ja": "それ、大丈夫なん？",
      "zh": "那真的沒問題嗎?"
    },
    {
      "ja": "そういう大輝はどうなん。大学、今年で卒業やろ",
      "zh": "那大輝你呢。今年大學畢業吧?"
    },
    {
      "ja": "それよりお前はエエ話は出てけーへんのか。東京に行って、もう六年やろ",
      "zh": "比起這個,你有沒有好消息啊?去東京已經六年了吧?"
    },
    {
      "ja": "あらやだ。あんた恋人出来たん？",
      "zh": "哎呀不會吧。你交到女朋友了?"
    },
    {
      "ja": "学生時代あんだけ振られまくってた佳亮が？　何処のもの好きなん",
      "zh": "學生時代被甩個沒完的佳亮?哪裡的奇人異士啊?"
    },
    {
      "ja": "おかん、ひどいわ。時間できたら連れてくるから会うてくれるか？　エエ人やで",
      "zh": "媽,妳太過分了啦。等有時間我帶她過來,你們見見好嗎?是個好人喔。"
    },
    {
      "ja": "連れてくるときは言いなさい。部屋を一部屋用意したる",
      "zh": "帶過來的時候要說一聲。我給你們準備一間房。"
    },
    {
      "ja": "うん、連絡するな。楽しみにしといて",
      "zh": "嗯,我會聯絡的。等著期待吧。"
    },
    {
      "ja": "薫子さ……、わあ",
      "zh": "薰子……哇。"
    },
    {
      "ja": "ごっ、ごめんね……。寝てた……",
      "zh": "對、對不起……。我剛還在睡……"
    },
    {
      "ja": "薫子さん、僕の事はエエから寝とってください。また落ち着いたらゆっくり食事しましょ？",
      "zh": "薰子小姐,別管我了,妳去睡吧。等妳緩過來再慢慢吃飯吧?"
    },
    {
      "ja": "ち……っ、違うの……。一緒にご飯、食べたい……",
      "zh": "不、不是的……。我想跟你一起吃飯……"
    },
    {
      "ja": "ほな薫子さん、コンビニ行きましょうか。今ならおでんだと体があったまります",
      "zh": "那薰子小姐,我們去便利商店吧。現在吃關東煮可以暖暖身子。"
    },
    {
      "ja": "薫子さん、何が好きですか？",
      "zh": "薰子小姐,妳喜歡什麼料?"
    },
    {
      "ja": "私はねー、大根とー、つくねとー、厚揚げとー、白滝。あっ、玉子もいいよね",
      "zh": "我啊—蘿蔔—雞肉丸子—厚揚豆腐—蒟蒻絲。啊,雞蛋也不錯。"
    },
    {
      "ja": "僕も大根と玉子がマストで、あとは白滝とかはんぺんとか、ロールキャベツも好きです",
      "zh": "我也是蘿蔔和雞蛋是必吃的,其他像蒟蒻絲、魚漿,還喜歡高麗菜捲。"
    },
    {
      "ja": "あはは、薫子さん、マスクは正解ですね。僕、顔が冷たいです",
      "zh": "哈哈,薰子小姐,戴口罩是正解。我的臉好冷。"
    },
    {
      "ja": "え…っ!?　ええ……っ!?",
      "zh": "咦……!?咦——!?"
    },
    {
      "ja": "……佳亮くん、変に思われるよ……",
      "zh": "……佳亮,會被人覺得奇怪喔……"
    },
    {
      "ja": "……おかしいですか？",
      "zh": "……奇怪嗎?"
    },
    {
      "ja": "……だって、私なんか遠目でみたら、男の人だよ……",
      "zh": "……因為,像我這樣的人遠遠看就是個男的……"
    },
    {
      "ja": "……という訳で、僕ちょっと、望月さんとお話して来ようと思てるんです。望月さんのお宅を教えて貰えませんか？",
      "zh": "……所以,我打算跟望月先生談談。可以告訴我望月先生家在哪嗎?"
    },
    {
      "ja": "……でも、仮にも婚約者の方が居らはって、僕が何もせずに横から薫子さんをとってしまう訳にはいきませんから……",
      "zh": "……可是,既然有未婚夫存在,我什麼都不做就從旁邊把薰子小姐搶走是不行的……"
    },
    {
      "ja": "……じゃあ、私が付き添っては駄目？　望月さんがどんな方法で佳亮くんを拒もうとするか、分からないわ。私が間に入れば……",
      "zh": "……那麼,我陪你去不行嗎?不知道望月先生會用什麼方法拒絕佳亮。我從中介入的話……"
    },
    {
      "ja": "薫子さん。薫子さんのことで男同士の話をするんですよ？　薫子さんが居て良いわけないでしょう？",
      "zh": "薰子小姐。為了薰子小姐的事我們是男人之間的對話喔?薰子小姐在場怎麼行呢?"
    },
    {
      "ja": "いずれ、薫子さんのご両親にも納得してもらわんとあきませんし、望月さんに納得いただけてへん今の状況は良くないと思います",
      "zh": "遲早也要讓薰子小姐的父母接受,望月先生不能接受的現狀,我覺得不好。"
    },
    {
      "ja": "……僕と望月さんで話さなければいけないことは、一つだけやと思います",
      "zh": "……我和望月先生必須談的事,只有一件吧。"
    },
    {
      "ja": "…君は彼女に相応しくない。身を引いてくれないか",
      "zh": "……你不配她。你能不能退出?"
    },
    {
      "ja": "薫子さんは僕との将来を考えてくれてはりますし、僕も、出来ればご両親に許して頂いていずれ結婚したいと思うてます。",
      "zh": "薰子小姐也考慮和我的未來,我也希望能得到她父母同意,將來結婚。"
    },
    {
      "ja": "僕の事を知らずに相応しくないと断じる前に、話し合いに応じてくれませんか",
      "zh": "在不了解我就斷定我不配之前,可不可以先談談?"
    },
    {
      "ja": "君では、彼女を悲しませるだけなんだ。どうか、引いて欲しい",
      "zh": "你只會讓她傷心。請你退出吧。"
    },
    {
      "ja": "君のご両親は、彼女を受け入れないだろう。その時に彼女が傷つくよりも、僕の許に来た方が良いと言っているんだ",
      "zh": "你的父母,不會接受她吧。與其到那時讓她受傷,不如來我身邊比較好。"
    },
    {
      "ja": "彼女に相応しいのは、彼女を守れる強い男だ。僕と勝負してくれないか",
      "zh": "配得上她的,是能保護她的強壯男人。能不能和我比試?"
    },
    {
      "ja": "おかしいですよね!?　そこに飾られてる表彰状とトロフィー、貴方のものやないですか！",
      "zh": "這不奇怪嗎!?那邊掛的獎狀和獎盃,不都是您的嗎!"
    },
    {
      "ja": "県大会優勝とか、全国大会の賞状とかもろてる人が、素人相手に本気ですか!?",
      "zh": "縣大會冠軍、全國大會獎狀都拿過的人,真的要對素人認真嗎!?"
    },
    {
      "ja": "彼女に相応しいよう、常に鍛錬してきた。勝負はこれしかない",
      "zh": "為了配得上她,我一直在鍛鍊。決勝負就只能這樣。"
    },
    {
      "ja": "受け身くらい取れるだろう！",
      "zh": "受身的動作總會吧!"
    },
    {
      "ja": "出来るわけないですよね!?　高校の時以來ですよ！",
      "zh": "怎麼可能會啊!?從高中之後就沒做過了!"
    },
    {
      "ja": "こんなことになるんやったら、紅葉狩りの後からジムに通ってればよかった！",
      "zh": "早知道會這樣,賞楓之後就該去健身房的!"
    },
    {
      "ja": "佑さん、もうやめて！",
      "zh": "佑先生,別再打了!"
    },
    {
      "ja": "薫子さん、これで分かったでしょう。貴女を守るのにふさわしいのは彼じゃない",
      "zh": "薰子小姐,這下妳明白了吧。配得上保護妳的不是他。"
    },
    {
      "ja": "体格差を分かっていて勝負するのはフェアじゃないわ",
      "zh": "知道體格差距還要比試,並不公平。"
    },
    {
      "ja": "柔よく剛を制すと言うでしょう！",
      "zh": "不是說「柔能克剛」嗎!"
    },
    {
      "ja": "佳亮くんに運動経験がないことは、分かると思うわ！",
      "zh": "佳亮沒有運動經驗,你看得出來吧!"
    },
    {
      "ja": "『勝負は嘘をつかない』、貴女の言葉でしたよね？",
      "zh": "「勝負不會說謊」,這是妳當時說的話對吧?"
    },
    {
      "ja": "それを支えに、僕は鍛錬を積んできました。今の結果を見れば分かるとお思いですが",
      "zh": "靠著這句話,我一直鍛鍊到現在。看現在的結果就應該明白才對。"
    },
    {
      "ja": "……そう思っていた時期もありました。でも、人の心は強さだけでは測れない、と、今の私は思います",
      "zh": "……我也曾經那麼想過。但是人的心,不能只用強弱來衡量,現在的我這麼認為。"
    },
    {
      "ja": "彼が貴女を傷つけることになってもですか！",
      "zh": "就算他會傷害妳也一樣嗎!"
    },
    {
      "ja": "女だからって、守られるばかりではないの。傷ついても欲しいものはあるわ",
      "zh": "身為女人,並不是只能被守護。就算受傷也有想要的東西。"
    },
    {
      "ja": "全国大会優勝、おめでとうございます",
      "zh": "全國大會優勝,恭喜你。"
    },
    {
      "ja": "勲章ですよ。貴女の隣に立つという",
      "zh": "這是勳章喔。站在妳身邊的勳章。"
    },
    {
      "ja": "…私には大滝は重いです",
      "zh": "……大瀧這個招牌對我來說太沉重了。"
    },
    {
      "ja": "僕が支えます",
      "zh": "我會支持妳的。"
    },
    {
      "ja": "……佑さんは、望月を重たいと思ったことはない？",
      "zh": "……佑先生,你不曾覺得望月家很沉重嗎?"
    },
    {
      "ja": "僕の根幹ですから",
      "zh": "因為那是我的根本。"
    },
    {
      "ja": "僕、カッコ悪かったですね",
      "zh": "我剛剛真是太遜了。"
    },
    {
      "ja": "佳亮くんが良いのは、そういう所じゃないの",
      "zh": "佳亮的好,不是在那種地方。"
    },
    {
      "ja": "二人三脚って、良く言うじゃない",
      "zh": "不是常說兩人三腳嗎?"
    },
    {
      "ja": "そうよ。結局は、其処へ行きつくんだと思うわ",
      "zh": "對啊。我覺得最終就是要走到那一步。"
    },
    {
      "ja": "そっか。もうそろそろ花見の季節やなあ",
      "zh": "對啊。差不多到了賞花的季節了。"
    },
    {
      "ja": "お花見かあ…。毎年家族で家の桜を見ているわ。",
      "zh": "賞花啊……。每年家人都會看家裡的櫻花。"
    },
    {
      "ja": "祖父がもう年だから、人ごみには行けなくて、久しく公園とかで家族のお花見してないのよ。",
      "zh": "祖父年紀大了,沒辦法去人多的地方,所以很久沒在公園跟家人賞花了。"
    },
    {
      "ja": "それが惜しいわ",
      "zh": "覺得可惜呢。"
    },
    {
      "ja": "良ければ、一緒に見に行きませんか？",
      "zh": "如果可以的話,要不要一起去看?"
    },
    {
      "ja": "上野の桜とか、中川の桜とか、色々選べますし。勿論、おうちの了承が取れたら、ですけど",
      "zh": "上野的櫻花、中川的櫻花,有很多選擇。當然,要徵得家裡同意才行。"
    },
    {
      "ja": "えっ、祖父が良いと言えば、是非行きたいわ",
      "zh": "咦?如果祖父說好,我很想去。"
    },
    {
      "ja": "うう、厳しく追及されそうですね……",
      "zh": "嗚,看來會被嚴格盤問啊……"
    },
    {
      "ja": "せめて、何かお土産を持って行きましょう。ご家族の好物とかありますか？",
      "zh": "至少帶點伴手禮去吧。家人有什麼喜歡的東西嗎?"
    },
    {
      "ja": "おじいさまは筑前煮が好きなのよ。今も平田に別で作らせるくらい。",
      "zh": "祖父喜歡筑前煮。現在還會單獨叫平田做。"
    },
    {
      "ja": "でも一番好きなのはおばあさまが作られた筑前煮ね",
      "zh": "但最喜歡的是祖母做的筑前煮。"
    },
    {
      "ja": "取り敢えず酸味を利かせたお弁当でも作ってみます。",
      "zh": "總之先做一些帶點酸味的便當試試。"
    },
    {
      "ja": "薫子さんに対する誠意だけは持っているつもりなので、頑張ります",
      "zh": "至少對薰子小姐的誠意是有的,我會努力的。"
    },
    {
      "ja": "ようこそおいでくださいました、杉山さま",
      "zh": "歡迎您大駕光臨,杉山先生。"
    },
    {
      "ja": "お邪魔します、白樺さん",
      "zh": "打擾了,白樺先生。"
    },
    {
      "ja": "杉山さまがおいでです",
      "zh": "杉山先生來了。"
    },
    {
      "ja": "いらっしゃい、佳亮くん。どうぞ入って",
      "zh": "歡迎,佳亮。請進。"
    },
    {
      "ja": "お邪魔します",
      "zh": "打擾了。"
    },
    {
      "ja": "初めまして、杉山佳亮と申します。この度はお誘いいただきありがとうございます",
      "zh": "初次見面,我叫杉山佳亮。這次承蒙邀請,非常感謝。"
    },
    {
      "ja": "やあ、会えてうれしいよ。僕は大瀧樹。薫子の兄だ。",
      "zh": "嗨,很高興見到你。我是大瀧樹,薰子的哥哥。"
    },
    {
      "ja": "ようおいでなすった。まあ、君も掛けなさい",
      "zh": "歡迎你來。來,你也坐吧。"
    },
    {
      "ja": "あの、これ、皆さんで召し上がってください",
      "zh": "那個,這個請大家享用。"
    },
    {
      "ja": "まあ、薫子。佑さんとのお話を断ったというから、どんな青年かと思っていたのに、なんて平凡な男性なの",
      "zh": "哎呀,薰子。聽說妳拒絕了和佑先生的話,還想說是什麼樣的青年,沒想到這麼平凡的男性。"
    },
    {
      "ja": "お母様",
      "zh": "母親。"
    },
    {
      "ja": "佑くんとは付き合いの長さが違うじゃろう。杉山くんが悪いわけではないわな",
      "zh": "和佑的交往時間長度不同嘛。杉山並沒有錯。"
    },
    {
      "ja": "今度お伺いするときは、ゼリー寄せを持ってきます。存じ上げず、申し訳ありませんでした",
      "zh": "下次拜訪時,我會帶果凍凍。沒有事先得知,十分抱歉。"
    },
    {
      "ja": "まあ。厚顔だこと。二度目があるとお思い？",
      "zh": "哎呀,真厚臉皮。你以為還有下次嗎?"
    },
    {
      "ja": "わたくし、彼を息子と呼ぶのは嫌よ。お父さまも肩を持ってばかりいないでくださいな",
      "zh": "我可不要叫他兒子。父親請別老是袒護他。"
    },
    {
      "ja": "ふむ。しかし杉山くんは良い青年じゃよ。杉山くん。この爺の顔に見覚えはないかな？",
      "zh": "嗯。但杉山是個好青年喔。杉山。對這個老頭子的臉沒有印象嗎?"
    },
    {
      "ja": "あ……、あの時にお孫さんの為にモンブランを買っていかれた……？",
      "zh": "啊……,那時為了孫女買蒙布朗的那位……?"
    },
    {
      "ja": "薫子がアパートから帰ってきておると聞いて、君の顔も見てみたかったからあそこまで出向いてみたんじゃ。",
      "zh": "聽說薰子從公寓回家了,我也想看看你的長相,所以特意去那邊看看。"
    },
    {
      "ja": "あの時はあとから手を出したにもかかわらず、快く譲ってくれてありがとうな",
      "zh": "那時我後伸的手,你還爽快地讓給我,謝謝你啊。"
    },
    {
      "ja": "薫子が急に平田に料理を習い始めたというのでな。失礼かと思ったが、調べさせてもらった。",
      "zh": "薰子突然開始跟平田學料理,雖然失禮但我去調查了。"
    },
    {
      "ja": "祥子、杉山くんは品行方正な良い青年じゃよ。佑くんにも劣らんと思うぞ、儂は",
      "zh": "祥子,杉山是個品行端正的好青年喔。我覺得不亞於佑。"
    },
    {
      "ja": "ところでその脇に抱えておるのはなんじゃ",
      "zh": "對了,你那邊抱著的是什麼?"
    },
    {
      "ja": "ほう、これは見事だ。おひとりで作られたのかな？",
      "zh": "哦,真精緻。是你一個人做的嗎?"
    },
    {
      "ja": "あ、はい。僕は料理しか得意なことがなくて……",
      "zh": "啊,是的。我除了料理沒別的擅長的事……"
    },
    {
      "ja": "……んむ。美味い。ばあさんの味とは違うが、さっぱりとしておって食べやすい",
      "zh": "……嗯,好吃。雖然跟老婆子的味道不同,但很清爽很好入口。"
    },
    {
      "ja": "ほ、本当ですか",
      "zh": "真、真的嗎?"
    },
    {
      "ja": "ん……。……あら、懐かしい味。子供の頃におかあさまが作ってくださった味だわ",
      "zh": "嗯……。哎呀,懷念的味道。是小時候媽媽做給我的味道。"
    },
    {
      "ja": "うん、この玉子焼き美味しいわ、佳亮くん",
      "zh": "嗯,這個玉子燒好吃,佳亮。"
    },
    {
      "ja": "レンコンハンバーグはビールのつまみにも良さそうだ",
      "zh": "蓮藕漢堡排當啤酒下酒菜也不錯。"
    },
    {
      "ja": "……さて、お養父さまが良くても、杉山くんのご両親が何と言うか、ですよ。",
      "zh": "……話雖如此,就算養父覺得好,杉山的父母會怎麼說呢。"
    },
    {
      "ja": "もし薫子を傷付けるようなことを言う方でしたら、そんな人が居る家へ薫子を嫁がせるのは、私は許しませんけどね",
      "zh": "如果是會說傷害薰子話的人,我可不允許薰子嫁到那種人在的家裡。"
    },
    {
      "ja": "それは薫子が何とかすることじゃ。儂らが出しゃばる場面じゃないじゃろう",
      "zh": "那是薰子要去處理的。不是我們該插手的場合吧。"
    },
    {
      "ja": "夏休みになる前やったらこっちも空いとるから来てもろてもエエよ",
      "zh": "暑假之前我們這邊有空,你帶她過來也可以。"
    },
    {
      "ja": "そう？　ほな、来週の週末にでも帰るわ。何か買っていくもんある？",
      "zh": "是嗎?那下週末就回去吧。要不要買什麼帶回去?"
    },
    {
      "ja": "そんなこと気にせんと。彼女の緊張解してやりぃさ",
      "zh": "別操心那種事。幫女朋友放鬆心情吧。"
    },
    {
      "ja": "なにか、問題があるんやろか……",
      "zh": "難道……有什麼問題嗎……"
    },
    {
      "ja": "秋になると紅葉もきれいなんですけど、梅雨は過ごしにくいだけで申し訳ないです。",
      "zh": "秋天的話楓葉很美,梅雨季只是悶熱不舒服,真不好意思。"
    },
    {
      "ja": "今度別の機会にご案内しますね",
      "zh": "下次有機會再帶妳來吧。"
    },
    {
      "ja": "う、うん……。でも、今はそこまで頭が回らないわ……。",
      "zh": "嗯、嗯……。不過,我現在沒辦法想那麼遠……"
    },
    {
      "ja": "無事にお父様お母様に気に入って頂けたら、誘ってくれる？",
      "zh": "如果順利讓令尊令堂喜歡我,你會再邀我嗎?"
    },
    {
      "ja": "おとんもおかんもいろんな人を受け入れてきた人たちや。他人を『看板』で判断したりせえへん……",
      "zh": "我爸媽都是接納過各種人的人。不會用「招牌」來評判他人……"
    },
    {
      "ja": "よう来はったね",
      "zh": "歡迎妳遠道而來。"
    },
    {
      "ja": "佳亮さんとお付き合いさせて頂いております、大瀧薫子と申します",
      "zh": "我和佳亮在交往,我叫大瀧薰子。"
    },
    {
      "ja": "あの、これご家族で",
      "zh": "那個,這個請家人享用。"
    },
    {
      "ja": "おお、……たき？",
      "zh": "喔,……瀧?"
    },
    {
      "ja": "あんた、……もしかして大瀧建設の娘か",
      "zh": "妳……難道是大瀧建設的女兒?"
    },
    {
      "ja": "大瀧の娘を、我が家に受け入れるわけにはいかへん",
      "zh": "大瀧家的女兒,我們家不能接納。"
    },
    {
      "ja": "……昔、私らが居た場所に、観光地再建だと言って大きなホテルと観光街を建てはったんが、大瀧建設や。",
      "zh": "……以前,在我們待的地方,大瀧建設說要重建觀光區,蓋了大飯店和觀光街。"
    },
    {
      "ja": "私らはあの場所を奪われて、こんな辺鄙な場所に移って来た。",
      "zh": "我們被奪走那個地方,搬到這麼偏僻的地方來。"
    },
    {
      "ja": "その時にあった資金でようやっと建てたこの旅館には、お客さんも半分以上戻ってきはらへん、売り上げは格段に落ちた。",
      "zh": "用當時剩下的資金好不容易蓋的這家旅館,客人也有一半以上沒回來,營業額大幅下降。"
    },
    {
      "ja": "あの時からの悔しさを、私らは忘れてへん",
      "zh": "從那時開始的憤恨,我們不會忘記。"
    },
    {
      "ja": "……おかんもおとんも、薫子さんの人柄に触れたら考えを変えます。辛い思いをさせてしまって、すみません……",
      "zh": "……我爸媽接觸到薰子小姐的人品後會改變想法的。讓妳這麼難過,真對不起……"
    },
    {
      "ja": "ううん、佳亮くんが謝ることじゃないわ。……それに、お母様の気持ちも良く分かるから……。",
      "zh": "不,佳亮你不需要道歉。……再說,母親的心情我也很懂……"
    },
    {
      "ja": "私は私のやるべきことを考えるわ",
      "zh": "我會想想我該做的事。"
    },
    {
      "ja": "なんとかお父様とお母様に認めて頂きたいの。私に出来ることを探すわ",
      "zh": "我想盡辦法讓令尊令堂認可我。我會找找我能做的事。"
    },
    {
      "ja": "佳亮。あの娘（こ）だけはアカン。この旅館が被（こうむ）った災難を忘れるわけにはいかん",
      "zh": "佳亮。那個女孩不行。我們不能忘記這家旅館遭受過的災難。"
    },
    {
      "ja": "薫子さん本人が悪いわけちゃうやろ？",
      "zh": "薰子小姐本人並沒有錯吧?"
    },
    {
      "ja": "薫子さんは今までずっと自分の実家の名前を負わされていて、でもそれに甘んじることなく仕事をしてきた人なんや。",
      "zh": "薰子小姐一直背負著娘家的名字,卻沒有甘於現狀,一直認真工作。"
    },
    {
      "ja": "俺も大瀧建設の薫子さんを好きになったわけとちゃう。人としての薫子さんを好きになったんや。",
      "zh": "我不是喜歡上大瀧建設的薰子小姐。是喜歡上身為一個人的薰子小姐。"
    },
    {
      "ja": "それをおとんとおかんには分かって欲しい",
      "zh": "希望爸媽能理解這一點。"
    },
    {
      "ja": "あの娘を受け入れるには、私らの気持ちも整理させてもらわなあかん。急には無理や",
      "zh": "要接受那個女孩,我們的心情也需要整理。突然不行的。"
    },
    {
      "ja": "本当なんだわ……。じゃあ、住み慣れた土地を離れなければならなかったご両親のお怒りは尤もだわ……",
      "zh": "是真的啊……。那麼,被迫離開住慣的土地的父母會生氣是理所當然的……"
    },
    {
      "ja": "もしもし、佑さん。夜分に恐れ入ります、薫子です。実は、折り入ってお願いしたいことがあるんですが……",
      "zh": "喂,佑先生。夜深叨擾不好意思,我是薰子。其實,我有件事想拜託您……"
    },
    {
      "ja": "……薫子さん、両親のことを気にされてるのなら、僕が何とか説得するので、あまり気にしないでください。",
      "zh": "……薰子小姐,如果妳在意我父母的事,我會想辦法說服他們,請別太放在心上。"
    },
    {
      "ja": "両親も良い大人ですし、何時までも意地を張っているわけではありません。",
      "zh": "我父母都是成年人,不會一直鬧脾氣的。"
    },
    {
      "ja": "うん、ありがとう。でも、大瀧がご両親のプライドに傷をつけたのなら、私はそれを償わなくてはならないわ。",
      "zh": "嗯,謝謝。但是,如果大瀧傷害了你父母的尊嚴,我就必須彌補。"
    },
    {
      "ja": "言うてください。必ず話が出来るよう、セッティングします",
      "zh": "請說。我一定會安排好讓你們能談談。"
    },
    {
      "ja": "今日はお時間取って頂いてありがとうございます。",
      "zh": "今天感謝您撥冗。"
    },
    {
      "ja": "まず、過去に大滝がご両親の事業に水を差したことを、心からお詫び申し上げます",
      "zh": "首先,對於過去大瀧妨礙了令尊令堂的事業,我由衷致歉。"
    },
    {
      "ja": "大瀧の所為で、こちらの旅館を急遽不慣れなこの土地に建てなくてはならなくなったと、この前お伺いしました。",
      "zh": "我前次聽說,因為大瀧的緣故,你們不得不臨時在這塊不熟悉的土地上蓋這家旅館。"
    },
    {
      "ja": "そこでお話があります。こちらの旅館の内装と付加価値のあるサービスを、ご提案させて頂けませんでしょうか",
      "zh": "因此我有個提議。能否讓我來提案這家旅館的內部裝潢與附加價值服務?"
    },
    {
      "ja": "失礼ながら、ホームページで旅館の画像を拝見させて頂きました。",
      "zh": "雖然失禮,我看了你們網站上旅館的照片。"
    },
    {
      "ja": "移転を急がれたようですので、その時から変わっておられないと思います。",
      "zh": "因為當時是急著遷移,所以應該都沒什麼變化。"
    },
    {
      "ja": "お客様に最もアピールするべき客室の内装を、私に手掛けさせてください",
      "zh": "最該向客人展現魅力的客房內裝,請讓我來負責。"
    },
    {
      "ja": "なんやと？",
      "zh": "什麼?"
    },
    {
      "ja": "私はリゾート施設の内装を手掛ける會社で働いております。良いお仕事をさせて頂くとお約束します。是非、この旅館の未来を手伝わせてください",
      "zh": "我在負責度假設施內裝的公司工作。我承諾會做出好成果。請務必讓我幫助這家旅館的未來。"
    },
    {
      "ja": "私はホテルサービスをご提供する会社に勤めております。",
      "zh": "我在提供旅館服務的公司工作。"
    },
    {
      "ja": "今回、近隣的飲食店からご協力を得ることが出来ました。",
      "zh": "這次,我獲得了附近餐飲店的協助。"
    },
    {
      "ja": "そのお店の方たちとコラボして、この旅館にお泊り頂く方だけではなく、新しいお客様を掘り起こしてみませんか？",
      "zh": "與那些店家合作,不只是住宿的客人,也來開發新客源如何?"
    },
    {
      "ja": "地の利が悪いとおっしゃっておられましたが、ここまで足を延ばされたお客さまにはこの旅館の窓から見える景色をお楽しみいただけます。",
      "zh": "您說地理位置不佳,但專程來到這裡的客人可以欣賞旅館窗外的景色。"
    },
    {
      "ja": "観光地らしかぬ自然の残った美しい風景。遠景に五重塔。",
      "zh": "不像觀光地、保有自然的美麗風景。遠處還有五重塔。"
    },
    {
      "ja": "そこで供される、地元ならではのランチやスイーツ。……つまり、デイユースを取り込むのです",
      "zh": "在那裡提供當地獨有的午餐和甜點。……也就是,把白天利用客群也納入進來。"
    },
    {
      "ja": "し、しかし、お泊り頂かんことには、経営は苦しい",
      "zh": "可、可是,沒有住宿的話,經營很困難。"
    },
    {
      "ja": "勿論、デイユースは足掛かりにすぎません。顧客の半分以上を失われた分は新規のお客様を確保せねばなりません。",
      "zh": "當然,白天利用只是踏腳石。失去半數以上顧客的部分必須開發新客源。"
    },
    {
      "ja": "部屋は見違えるほど良くします。ご両親のおもてなしさえあれば、きっと二度目はご宿泊に違いありません",
      "zh": "我會把房間整修到讓人認不出來。只要有令尊令堂的款待,客人第二次一定會來住宿的。"
    },
    {
      "ja": "しゃあない。そこまで言われて自分らの力、信用出来ひんなんて言われへん。",
      "zh": "沒辦法。被妳這樣說,可不能說自己沒信心。"
    },
    {
      "ja": "大船に乗った気持ちで任せてみるわ。大滝さん、この旅館をよろしゅう頼んます",
      "zh": "我就抱著靠大船的心情交給妳了。大瀧小姐,這家旅館就拜託妳了。"
    },
    {
      "ja": "薫子さん、望月さん。うちの為に、ありがとうございます……",
      "zh": "薰子小姐,望月先生。為了我家,真的感謝……"
    },
    {
      "ja": "や、止めてよ、佳亮くん。今までうちが関わった事業の中で、こうして犠牲になった人たちが居たんだと、改めて分かったわ。",
      "zh": "別、別這樣,佳亮。我這次才重新認識到,我們經手過的事業中有過這樣犧牲的人。"
    },
    {
      "ja": "だから私たちは胡坐をかいてちゃいけない。そう知れて、勉強になったのよ。お礼が言いたいのはこちらだわ",
      "zh": "所以我們不能坐享其成。能知道這點,我學到了很多。該道謝的是我們才對。"
    },
    {
      "ja": "僕も、今回の話はいい経験になった。悪い話ばかりではなかったよ、杉山くん",
      "zh": "我也是,這次的事是個好經驗。並不全是壞事啦,杉山。"
    },
    {
      "ja": "そんなの、薫子さんを幸せにすることでしか返せないだろう。君は知っている筈だ",
      "zh": "那種事,只能靠讓薰子小姐幸福來回報吧。你應該知道的。"
    },
    {
      "ja": "おとん、おかん。薫子さんとの交際、認めてもらえますか？",
      "zh": "爸、媽。我和薰子小姐的交往,能讓你們認可嗎?"
    },
    {
      "ja": "あんた、このやり取りを見て、認めんなんて言葉、出てくると思うてへんやろ",
      "zh": "你看了這場互動,該不會還以為我能說出「不認可」這種話吧。"
    },
    {
      "ja": "大瀧さんには改めて奈良に来てもらいたい。……新しくなった部屋に客として泊って欲しい",
      "zh": "希望大瀧小姐再來奈良一趟。……希望妳以客人身分住住看翻新後的房間。"
    },
    {
      "ja": "あー、今日は緊張したなあ。まさかお二人であんな話を仕組んでいたなんて",
      "zh": "啊—今天好緊張啊。沒想到妳們兩個策劃了那樣的事。"
    },
    {
      "ja": "だって、これは佳亮くんのご両親と大瀧の話だもの。私が解決しなきゃいけない話だったのよ。……佑さんは巻き込まれてしまって災難だったけど",
      "zh": "因為這是佳亮父母和大瀧之間的事嘛。是我必須解決的事。……雖然佑先生被捲進來算是倒霉了。"
    },
    {
      "ja": "いや。僕は薫子さんと一緒に仕事が出来て嬉しかったよ。また会いましょう。……杉山くんには報告をして",
      "zh": "不。我能跟薰子小姐一起工作很開心。再見吧。……要跟杉山報告的。"
    },
    {
      "ja": "そんな狭い目で見ませんよ……。お二人とも、恩人だ。奈良に足を運んだときは、是非泊ってくださいね",
      "zh": "我不會這麼小心眼啦……。兩位都是恩人。下次到奈良時,請務必來住宿。"
    },
    {
      "ja": "是非そうさせてもらおう",
      "zh": "務必如此。"
    },
    {
      "ja": "私もお義父さまにお誘い頂いたし、勿論よ",
      "zh": "我也受公公邀請了,當然會去。"
    },
    {
      "ja": "今日は本当にお疲れさまでした。何でも好きなご飯作りますよ、何が良いですか？",
      "zh": "今天真的辛苦了。我會做任何妳喜歡的飯,要吃什麼?"
    },
    {
      "ja": "そうねえ、じゃあ……",
      "zh": "我想想……那麼……"
    },
    {
      "ja": "世界で一番美味しいご飯",
      "zh": "世界上最好吃的飯。"
    },
    {
      "ja": "これからも薫子の為に美味しいご飯を沢山作ろう。",
      "zh": "今後也為薰子做許多美味的飯吧。"
    },
    {
      "ja": "美味しいご飯は、人生を豊かにするのだ",
      "zh": "美味的飯,能讓人生變得豐盛。"
    }
  ]
}